[
	{
		"LABEL": "0x0",
		"Type": "CLOSE_WINDOW",
		"SUBCMD": 1,
		"Args": "0d00"
	},
	{
		"LABEL": "0x6",
		"Type": "IMAGELOAD",
		"SUBCMD": 0,
		"Args": "00003d00000000000000"
	},
	{
		"LABEL": "0x14",
		"Type": "EQUN",
		"SUBCMD": 0,
		"Args": "3b1a0000"
	},
	{
		"LABEL": "0x1c",
		"Type": "DRAW",
		"SUBCMD": 0,
		"Args": "3c00"
	},
	{
		"LABEL": "0x22",
		"Type": "WAIT",
		"SUBCMD": 0,
		"Args": ""
	},
	{
		"LABEL": "0x26",
		"Type": "IMAGELOAD",
		"SUBCMD": 1,
		"Args": "11000100d76e00008002b4008100"
	},
	{
		"LABEL": "0x38",
		"Type": "DRAW",
		"SUBCMD": 0,
		"Args": "0f00"
	},
	{
		"LABEL": "0x3e",
		"Type": "MESSAGE",
		"SUBCMD": 3,
		"SUBCMD2": 18,
		"MSGID": 0,
		"VOICEID": 5064,
		"NameJPN": "鏡子",
		"JPN": "「すごいね、羽依里君」",
		"NameENG": "Kyouko",
		"ENG": "\"You're amazing, Hairi-kun!\"",
		"Args": "0b"
	},
	{
		"LABEL": "0x6c",
		"Type": "MESSAGE",
		"SUBCMD": 3,
		"SUBCMD2": 20,
		"MSGID": 1,
		"NameJPN": "羽依里",
		"JPN": "「昨日のあれ、ですか」",
		"NameENG": "Hairi",
		"ENG": "\"You mean that thing from yesterday?\"",
		"Args": "0b"
	},
	{
		"LABEL": "0x9c",
		"Type": "MESSAGE",
		"SUBCMD": 3,
		"SUBCMD2": 22,
		"MSGID": 2,
		"JPN": "小鳩さんとの大立ち回りが、早速噂になっているらしい。",
		"ENG": "Apparently, word of my showdown with Kobato-san had spread through the town like wildfire.",
		"Args": "0b"
	},
	{
		"LABEL": "0xe0",
		"Type": "MESSAGE",
		"SUBCMD": 3,
		"SUBCMD2": 24,
		"MSGID": 3,
		"NameJPN": "羽依里",
		"JPN": "「いや、まぁ」",
		"NameENG": "Hairi",
		"ENG": "\"I mean, y'know.\"",
		"Args": "0b"
	},
	{
		"LABEL": "0x108",
		"Type": "MESSAGE",
		"SUBCMD": 3,
		"SUBCMD2": 26,
		"MSGID": 4,
		"JPN": "ちょっと驚かせてしまったかもしれない。",
		"ENG": "I guess the news must've been pretty surprising for her.",
		"Args": "0b"
	},
	{
		"LABEL": "0x13e",
		"Type": "MESSAGE",
		"SUBCMD": 3,
		"SUBCMD2": 28,
		"MSGID": 5,
		"NameJPN": "羽依里",
		"JPN": "「意外な一面、見せてしまったかもしれませんね」",
		"NameENG": "Hairi",
		"ENG": "\"I guess that must have been kinda unexpected coming from me.\"",
		"Args": "0b"
	},
	{
		"LABEL": "0x186",
		"Type": "MOVE",
		"SUBCMD": 1,
		"Args": "1e0001000218009001b400"
	},
	{
		"LABEL": "0x196",
		"Type": "IMAGELOAD",
		"SUBCMD": 0,
		"Args": "010170ac00007003b4009100"
	},
	{
		"LABEL": "0x1a6",
		"Type": "DRAW",
		"SUBCMD": 0,
		"Args": "0f00"
	},
	{
		"LABEL": "0x1ac",
		"Type": "MESSAGE",
		"SUBCMD": 3,
		"SUBCMD2": 31,
		"MSGID": 6,
		"VOICEID": 28167,
		"NameJPN": "うみ",
		"JPN": "「なにやったの？」",
		"NameENG": "Umi",
		"ENG": "\"What'd you do!?\"",
		"Args": "0b"
	},
	{
		"LABEL": "0x1d6",
		"Type": "IMAGEUPDATE",
		"SUBCMD": 1,
		"Args": "21000100016f"
	},
	{
		"LABEL": "0x1e0",
		"Type": "DRAW",
		"SUBCMD": 0,
		"Args": "0f00"
	},
	{
		"LABEL": "0x1e6",
		"Type": "MESSAGE",
		"SUBCMD": 3,
		"SUBCMD2": 34,
		"MSGID": 7,
		"VOICEID": 5066,
		"NameJPN": "鏡子",
		"JPN": "「知らないの??」",
		"NameENG": "Kyouko",
		"ENG": "\"You haven't heard?\"",
		"Args": "0b"
	},
	{
		"LABEL": "0x210",
		"Type": "IMAGEUPDATE",
		"SUBCMD": 1,
		"Args": "24000100d16e"
	},
	{
		"LABEL": "0x21a",
		"Type": "DRAW",
		"SUBCMD": 0,
		"Args": "0f00"
	},
	{
		"LABEL": "0x220",
		"Type": "MESSAGE",
		"SUBCMD": 3,
		"SUBCMD2": 37,
		"MSGID": 8,
		"VOICEID": 5067,
		"NameJPN": "鏡子",
		"JPN": "「羽依里君がおじーさんをやっつけたんだよ」",
		"NameENG": "Kyouko",
		"ENG": "\"Hairi-kun actually put down the old man!\"",
		"Args": "0b"
	},
	{
		"LABEL": "0x262",
		"Type": "IMAGEUPDATE",
		"SUBCMD": 1,
		"Args": "2700010174ae"
	},
	{
		"LABEL": "0x26c",
		"Type": "DRAW",
		"SUBCMD": 0,
		"Args": "0f00"
	},
	{
		"LABEL": "0x272",
		"Type": "MESSAGE",
		"SUBCMD": 3,
		"SUBCMD2": 40,
		"MSGID": 9,
		"VOICEID": 28168,
		"NameJPN": "うみ",
		"JPN": "「すごーーい！　おにーちゃんつよいんだー」",
		"NameENG": "Umi",
		"ENG": "\"Wooowww! Onii-chan, you're so strong!\"",
		"Args": "0b"
	},
	{
		"LABEL": "0x2b4",
		"Type": "MESSAGE",
		"SUBCMD": 3,
		"SUBCMD2": 42,
		"MSGID": 10,
		"NameJPN": "羽依里",
		"JPN": "「鏡子さん、ちょっと説明がざっくりすぎです」",
		"NameENG": "Hairi",
		"ENG": "\"Kyouko-san, that's a little too abridged of an explanation.\"",
		"Args": "0b"
	},
	{
		"LABEL": "0x2fa",
		"Type": "IMAGEUPDATE",
		"SUBCMD": 1,
		"Args": "2c000100256f"
	},
	{
		"LABEL": "0x304",
		"Type": "DRAW",
		"SUBCMD": 0,
		"Args": "0f00"
	},
	{
		"LABEL": "0x30a",
		"Type": "MESSAGE",
		"SUBCMD": 3,
		"SUBCMD2": 45,
		"MSGID": 11,
		"VOICEID": 5069,
		"NameJPN": "鏡子",
		"JPN": "「それでね、その結果」",
		"NameENG": "Kyouko",
		"ENG": "\"And thanks to that...\"",
		"Args": "0b"
	},
	{
		"LABEL": "0x338",
		"Type": "IMAGEUPDATE",
		"SUBCMD": 1,
		"Args": "2f000100196f"
	},
	{
		"LABEL": "0x342",
		"Type": "DRAW",
		"SUBCMD": 0,
		"Args": "0f00"
	},
	{
		"LABEL": "0x348",
		"Type": "MESSAGE",
		"SUBCMD": 3,
		"SUBCMD2": 48,
		"MSGID": 12,
		"VOICEID": 5070,
		"NameJPN": "鏡子",
		"JPN": "「結婚することになったんだって」",
		"NameENG": "Kyouko",
		"ENG": "\"I heard he'll be getting married!\"",
		"Args": "0b"
	},
	{
		"LABEL": "0x380",
		"Type": "IMAGEUPDATE",
		"SUBCMD": 1,
		"Args": "3200010150ae"
	},
	{
		"LABEL": "0x38a",
		"Type": "CUSTOMMOVE",
		"SUBCMD": 0,
		"Args": "01010400"
	},
	{
		"LABEL": "0x392",
		"Type": "DRAW",
		"SUBCMD": 0,
		"Args": "0f00"
	},
	{
		"LABEL": "0x398",
		"Type": "MESSAGE",
		"SUBCMD": 3,
		"SUBCMD2": 51,
		"MSGID": 13,
		"VOICEID": 28169,
		"NameJPN": "うみ",
		"JPN": "「おじーさんと!?」",
		"NameENG": "Umi",
		"ENG": "\"To the old man!?\"",
		"Args": "0b"
	},
	{
		"LABEL": "0x3c4",
		"Type": "MESSAGE",
		"SUBCMD": 3,
		"SUBCMD2": 53,
		"MSGID": 14,
		"NameJPN": "羽依里",
		"JPN": "「だから説明がざっくりとしすぎですって」",
		"NameENG": "Hairi",
		"ENG": "\"Seriously, your explanations are way too hard to follow, Kyouko-san!\"",
		"Args": "0b"
	},
	{
		"LABEL": "0x406",
		"Type": "IMAGEUPDATE",
		"SUBCMD": 1,
		"Args": "37000100eb6f"
	},
	{
		"LABEL": "0x410",
		"Type": "DRAW",
		"SUBCMD": 0,
		"Args": "0f00"
	},
	{
		"LABEL": "0x416",
		"Type": "MESSAGE",
		"SUBCMD": 3,
		"SUBCMD2": 56,
		"MSGID": 15,
		"VOICEID": 5072,
		"NameJPN": "鏡子",
		"JPN": "「そうかしら」",
		"NameENG": "Kyouko",
		"ENG": "\"Oh, are they?\"",
		"Args": "0b"
	},
	{
		"LABEL": "0x43c",
		"Type": "IMAGEUPDATE",
		"SUBCMD": 1,
		"Args": "3a000100e56f"
	},
	{
		"LABEL": "0x446",
		"Type": "DRAW",
		"SUBCMD": 0,
		"Args": "0f00"
	},
	{
		"LABEL": "0x44c",
		"Type": "MESSAGE",
		"SUBCMD": 3,
		"SUBCMD2": 59,
		"MSGID": 16,
		"VOICEID": 5073,
		"NameJPN": "鏡子",
		"JPN": "「おじーさんのお孫さんとよ」",
		"NameENG": "Kyouko",
		"ENG": "\"He'll be marrying the old man's granddaughter.\"",
		"Args": "0b"
	},
	{
		"LABEL": "0x480",
		"Type": "IMAGEUPDATE",
		"SUBCMD": 1,
		"Args": "3d00010170ac"
	},
	{
		"LABEL": "0x48a",
		"Type": "DRAW",
		"SUBCMD": 0,
		"Args": "0f00"
	},
	{
		"LABEL": "0x490",
		"Type": "MESSAGE",
		"SUBCMD": 3,
		"SUBCMD2": 63,
		"MSGID": 17,
		"NameJPN": "羽依里",
		"JPN": "「もう皆知ってるんですね」",
		"NameENG": "Hairi",
		"ENG": "\"Guess everyone's already heard the news, huh?\"",
		"Args": "0b"
	},
	{
		"LABEL": "0x4c4",
		"Type": "IMAGEUPDATE",
		"SUBCMD": 1,
		"Args": "41000100d16e"
	},
	{
		"LABEL": "0x4ce",
		"Type": "DRAW",
		"SUBCMD": 0,
		"Args": "0f00"
	},
	{
		"LABEL": "0x4d4",
		"Type": "MESSAGE",
		"SUBCMD": 3,
		"SUBCMD2": 66,
		"MSGID": 18,
		"VOICEID": 5075,
		"NameJPN": "鏡子",
		"JPN": "「皆知ってるよ」",
		"NameENG": "Kyouko",
		"ENG": "\"That's right, everyone knows!\"",
		"Args": "0b"
	},
	{
		"LABEL": "0x4fc",
		"Type": "IMAGEUPDATE",
		"SUBCMD": 1,
		"Args": "4400010152ac"
	},
	{
		"LABEL": "0x506",
		"Type": "DRAW",
		"SUBCMD": 0,
		"Args": "0f00"
	},
	{
		"LABEL": "0x50c",
		"Type": "MESSAGE",
		"SUBCMD": 3,
		"SUBCMD2": 69,
		"MSGID": 19,
		"VOICEID": 28170,
		"NameJPN": "うみ",
		"JPN": "「おにーちゃんがけっこん……」",
		"NameENG": "Umi",
		"ENG": "\"Onii-chan's getting married...\"",
		"Args": "0b"
	},
	{
		"LABEL": "0x542",
		"Type": "MESSAGE",
		"SUBCMD": 3,
		"SUBCMD2": 71,
		"MSGID": 20,
		"NameJPN": "羽依里",
		"JPN": "「まねごとだよ」",
		"NameENG": "Hairi",
		"ENG": "\"It's just a pretense.\"",
		"Args": "0b"
	},
	{
		"LABEL": "0x56c",
		"Type": "FADE",
		"SUBCMD": 1,
		"Args": "49000100000f00"
	},
	{
		"LABEL": "0x578",
		"Type": "FADE",
		"SUBCMD": 0,
		"Args": "0101000f00"
	},
	{
		"LABEL": "0x582",
		"Type": "DRAW",
		"SUBCMD": 0,
		"Args": "0f00"
	},
	{
		"LABEL": "0x588",
		"Type": "MESSAGE",
		"SUBCMD": 3,
		"SUBCMD2": 75,
		"MSGID": 21,
		"JPN": "……おおまかに、うみちゃんに説明する。",
		"ENG": "...I gave Umi-chan a quick explanation.",
		"Args": "0b"
	},
	{
		"LABEL": "0x5be",
		"Type": "IMAGELOAD",
		"SUBCMD": 1,
		"Args": "4d00010010ac00008002b4009100"
	},
	{
		"LABEL": "0x5d0",
		"Type": "DRAW",
		"SUBCMD": 0,
		"Args": "0f00"
	},
	{
		"LABEL": "0x5d6",
		"Type": "MESSAGE",
		"SUBCMD": 3,
		"SUBCMD2": 78,
		"MSGID": 22,
		"VOICEID": 28171,
		"NameJPN": "うみ",
		"JPN": "「やっぱり、すごーーい」",
		"NameENG": "Umi",
		"ENG": "\"You really are amazing after all!\"",
		"Args": "0b"
	},
	{
		"LABEL": "0x606",
		"Type": "MESSAGE",
		"SUBCMD": 3,
		"SUBCMD2": 80,
		"MSGID": 23,
		"NameJPN": "羽依里",
		"JPN": "「そ、そうかな」",
		"NameENG": "Hairi",
		"ENG": "\"A-Am I?\"",
		"Args": "0b"
	},
	{
		"LABEL": "0x630",
		"Type": "RETURN",
		"SUBCMD": 1,
		"Args": "5600"
	},
	{
		"LABEL": "0x636",
		"Type": "END",
		"SUBCMD": 3,
		"Args": "58000080"
	}
]