[
	{
		"LABEL": "0x0",
		"Type": "CLOSE_WINDOW",
		"SUBCMD": 1,
		"Args": "0c00"
	},
	{
		"LABEL": "0x6",
		"Type": "IMAGELOAD",
		"SUBCMD": 0,
		"Args": "00003d00000000000000"
	},
	{
		"LABEL": "0x14",
		"Type": "EQUN",
		"SUBCMD": 0,
		"Args": "3b1a0000"
	},
	{
		"LABEL": "0x1c",
		"Type": "DRAW",
		"SUBCMD": 0,
		"Args": "3c00"
	},
	{
		"LABEL": "0x22",
		"Type": "WAIT",
		"SUBCMD": 0,
		"Args": ""
	},
	{
		"LABEL": "0x26",
		"Type": "MESSAGE",
		"SUBCMD": 3,
		"SUBCMD2": 14,
		"MSGID": 0,
		"NameJPN": "羽依里",
		"JPN": "「おはよう」",
		"NameENG": "Hairi",
		"ENG": "\"Morning.\"",
		"Args": "0b"
	},
	{
		"LABEL": "0x4c",
		"Type": "IMAGELOAD",
		"SUBCMD": 1,
		"Args": "1000010078ad00008002b4009100"
	},
	{
		"LABEL": "0x5e",
		"Type": "DRAW",
		"SUBCMD": 0,
		"Args": "0f00"
	},
	{
		"LABEL": "0x64",
		"Type": "MESSAGE",
		"SUBCMD": 3,
		"SUBCMD2": 18,
		"MSGID": 1,
		"VOICEID": 28247,
		"NameJPN": "うみ",
		"JPN": "「ずず、おはよー」",
		"NameENG": "Umi",
		"ENG": "\"*Slurp*... Morning.\"",
		"Args": "0b"
	},
	{
		"LABEL": "0x8e",
		"Type": "MESSAGE",
		"SUBCMD": 3,
		"SUBCMD2": 20,
		"MSGID": 2,
		"JPN": "うみちゃんがのんびりと、お茶を飲んでいた。",
		"ENG": "Umi-chan was leisurely drinking tea in the living room.",
		"Args": "0b"
	},
	{
		"LABEL": "0xc8",
		"Type": "IMAGEUPDATE",
		"SUBCMD": 1,
		"Args": "16000100dead"
	},
	{
		"LABEL": "0xd2",
		"Type": "DRAW",
		"SUBCMD": 0,
		"Args": "0f00"
	},
	{
		"LABEL": "0xd8",
		"Type": "MESSAGE",
		"SUBCMD": 3,
		"SUBCMD2": 24,
		"MSGID": 3,
		"VOICEID": 28248,
		"NameJPN": "うみ",
		"JPN": "「もう、きてるよー」",
		"NameENG": "Umi",
		"ENG": "\"She's already here.\"",
		"Args": "0b"
	},
	{
		"LABEL": "0x104",
		"Type": "MESSAGE",
		"SUBCMD": 3,
		"SUBCMD2": 26,
		"MSGID": 4,
		"NameJPN": "羽依里",
		"JPN": "「誰が」",
		"NameENG": "Hairi",
		"ENG": "\"Who?\"",
		"Args": "0b"
	},
	{
		"LABEL": "0x126",
		"Type": "IMAGEUPDATE",
		"SUBCMD": 1,
		"Args": "1c00010072ad"
	},
	{
		"LABEL": "0x130",
		"Type": "DRAW",
		"SUBCMD": 0,
		"Args": "0f00"
	},
	{
		"LABEL": "0x136",
		"Type": "MESSAGE",
		"SUBCMD": 3,
		"SUBCMD2": 30,
		"MSGID": 5,
		"VOICEID": 28249,
		"NameJPN": "うみ",
		"JPN": "「おともだちー」",
		"NameENG": "Umi",
		"ENG": "\"Your friend.\"",
		"Args": "0b"
	},
	{
		"LABEL": "0x15e",
		"Type": "MESSAGE",
		"SUBCMD": 3,
		"SUBCMD2": 32,
		"MSGID": 6,
		"NameJPN": "羽依里",
		"JPN": "「？」",
		"NameENG": "Hairi",
		"ENG": "\"...?\"",
		"Args": "0b"
	},
	{
		"LABEL": "0x17e",
		"Type": "IMAGELOAD",
		"SUBCMD": 1,
		"Args": "220006006b6c0900650061ff"
	},
	{
		"LABEL": "0x18e",
		"Type": "MESSAGE",
		"SUBCMD": 3,
		"SUBCMD2": 36,
		"MSGID": 7,
		"VOICEID": 10082,
		"NameJPN": "鴎",
		"JPN": "「あ、おはよう」",
		"NameENG": "Kamome",
		"ENG": "\"Ah, morning!\"",
		"Args": "0b"
	},
	{
		"LABEL": "0x1b4",
		"Type": "FADE",
		"SUBCMD": 1,
		"Args": "26000100000f00"
	},
	{
		"LABEL": "0x1c0",
		"Type": "DRAW",
		"SUBCMD": 0,
		"Args": "0f00"
	},
	{
		"LABEL": "0x1c6",
		"Type": "MESSAGE",
		"SUBCMD": 3,
		"SUBCMD2": 40,
		"MSGID": 8,
		"NameJPN": "羽依里",
		"JPN": "「え」",
		"NameENG": "Hairi",
		"ENG": "\"Huh?\"",
		"Args": "0b"
	},
	{
		"LABEL": "0x1e6",
		"Type": "MESSAGE",
		"SUBCMD": 3,
		"SUBCMD2": 42,
		"MSGID": 9,
		"JPN": "台所から聞こえるのは、鴎の声だ。",
		"ENG": "I heard Kamome's voice from the kitchen.",
		"Args": "0b"
	},
	{
		"LABEL": "0x216",
		"Type": "MESSAGE",
		"SUBCMD": 3,
		"SUBCMD2": 44,
		"MSGID": 10,
		"JPN": "そういえば、怪我をした俺の世話をしに来るとか、言ってたな。",
		"ENG": "Oh, right. She said something about taking care of me before.",
		"Args": "0b"
	},
	{
		"LABEL": "0x260",
		"Type": "MESSAGE",
		"SUBCMD": 3,
		"SUBCMD2": 46,
		"MSGID": 11,
		"NameJPN": "羽依里",
		"JPN": "「ほんとに来たのか」",
		"NameENG": "Hairi",
		"ENG": "\"You actually came?\"",
		"Args": "0b"
	},
	{
		"LABEL": "0x28e",
		"Type": "IMAGELOAD",
		"SUBCMD": 1,
		"Args": "300006006f6c0900650061ff"
	},
	{
		"LABEL": "0x29e",
		"Type": "MESSAGE",
		"SUBCMD": 3,
		"SUBCMD2": 50,
		"MSGID": 12,
		"VOICEID": 10083,
		"NameJPN": "鴎",
		"JPN": "「とーぜん」",
		"NameENG": "Kamome",
		"ENG": "\"But of course!\"",
		"Args": "0b"
	},
	{
		"LABEL": "0x2c0",
		"Type": "MESSAGE",
		"SUBCMD": 3,
		"SUBCMD2": 52,
		"MSGID": 13,
		"NameJPN": "羽依里",
		"JPN": "「って……」",
		"NameENG": "Hairi",
		"ENG": "\"Wait...\"",
		"Args": "0b"
	},
	{
		"LABEL": "0x2e6",
		"Type": "BGM",
		"SUBCMD": 1,
		"Args": "3600000000007800"
	},
	{
		"LABEL": "0x2f2",
		"Type": "MESSAGE",
		"SUBCMD": 3,
		"SUBCMD2": 56,
		"MSGID": 14,
		"JPN": "俺は思わず後ずさった。",
		"ENG": "I staggered backwards.",
		"Args": "0b"
	},
	{
		"LABEL": "0x318",
		"Type": "BGM",
		"SUBCMD": 1,
		"Args": "3a00a9860100"
	},
	{
		"LABEL": "0x322",
		"Type": "SETCGFLAG",
		"SUBCMD": 1,
		"Args": "3d005c04"
	},
	{
		"LABEL": "0x32a",
		"Type": "CLOSE_WINDOW",
		"SUBCMD": 0,
		"Args": ""
	},
	{
		"LABEL": "0x32e",
		"Type": "INIT",
		"SUBCMD": 0,
		"Args": "0100"
	},
	{
		"LABEL": "0x334",
		"Type": "IMAGELOAD",
		"SUBCMD": 0,
		"Args": "0000e305000000000000"
	},
	{
		"LABEL": "0x342",
		"Type": "SCALE",
		"SUBCMD": 0,
		"Args": "0000"
	},
	{
		"LABEL": "0x348",
		"Type": "MOVE",
		"SUBCMD": 0,
		"Args": "0000000000b6fd0aff"
	},
	{
		"LABEL": "0x356",
		"Type": "MOVE",
		"SUBCMD": 0,
		"Args": "00000c0e0167fff3ff"
	},
	{
		"LABEL": "0x364",
		"Type": "EVSCROLL",
		"SUBCMD": 0,
		"Args": "000000"
	},
	{
		"LABEL": "0x36c",
		"Type": "EQUN",
		"SUBCMD": 0,
		"Args": "3b1a0000"
	},
	{
		"LABEL": "0x374",
		"Type": "DRAW",
		"SUBCMD": 0,
		"Args": "3c00"
	},
	{
		"LABEL": "0x37a",
		"Type": "WAIT",
		"SUBCMD": 1,
		"Args": "3e007800"
	},
	{
		"LABEL": "0x382",
		"Type": "CLOSE_WINDOW",
		"SUBCMD": 1,
		"Args": "3f00"
	},
	{
		"LABEL": "0x388",
		"Type": "IMAGELOAD",
		"SUBCMD": 0,
		"Args": "00005c04000000000000"
	},
	{
		"LABEL": "0x396",
		"Type": "EQUN",
		"SUBCMD": 0,
		"Args": "3b1a0000"
	},
	{
		"LABEL": "0x39e",
		"Type": "DRAW",
		"SUBCMD": 0,
		"Args": "3c00"
	},
	{
		"LABEL": "0x3a4",
		"Type": "WAIT",
		"SUBCMD": 0,
		"Args": ""
	},
	{
		"LABEL": "0x3a8",
		"Type": "MESSAGE",
		"SUBCMD": 3,
		"SUBCMD2": 65,
		"MSGID": 15,
		"JPN": "朝、メイド服姿で仁王立ちする鴎がいた。",
		"ENG": "There she was. Kamome, standing tall and proud. In a maid uniform.",
		"Args": "0b"
	},
	{
		"LABEL": "0x3de",
		"Type": "MESSAGE",
		"SUBCMD": 3,
		"SUBCMD2": 67,
		"MSGID": 16,
		"NameJPN": "羽依里",
		"JPN": "「お前……なんだその格好は」",
		"NameENG": "Hairi",
		"ENG": "\"Why... are you wearing that?\"",
		"Args": "0b"
	},
	{
		"LABEL": "0x414",
		"Type": "MESSAGE",
		"SUBCMD": 3,
		"SUBCMD2": 69,
		"MSGID": 17,
		"VOICEID": 10084,
		"NameJPN": "鴎",
		"JPN": "「鏡子さんに、しばらくお手伝いさせていただきますって言ったら」",
		"NameENG": "Kamome",
		"ENG": "\"I asked Kyouko-san if she'd mind me lending a hand for a bit.\"",
		"Args": "0b"
	},
	{
		"LABEL": "0x468",
		"Type": "MESSAGE",
		"SUBCMD": 3,
		"SUBCMD2": 71,
		"MSGID": 18,
		"VOICEID": 10085,
		"NameJPN": "鴎",
		"JPN": "「じゃあ、これどうぞって」",
		"NameENG": "Kamome",
		"ENG": "\"And she gave me this!\"",
		"Args": "0b"
	},
	{
		"LABEL": "0x498",
		"Type": "IMAGELOAD",
		"SUBCMD": 1,
		"Args": "49000600296f0900790075ff"
	},
	{
		"LABEL": "0x4a8",
		"Type": "MESSAGE",
		"SUBCMD": 3,
		"SUBCMD2": 75,
		"MSGID": 19,
		"VOICEID": 10086,
		"NameJPN": "鏡子",
		"JPN": "「似合うでしょう」",
		"NameENG": "Kyouko",
		"ENG": "\"It really suits her, don't you think?\"",
		"Args": "0b"
	},
	{
		"LABEL": "0x4d2",
		"Type": "MESSAGE",
		"SUBCMD": 3,
		"SUBCMD2": 77,
		"MSGID": 20,
		"NameJPN": "羽依里",
		"JPN": "「ま、まぁ……似合うかな」",
		"NameENG": "Hairi",
		"ENG": "\"I-I mean, well, sure.\"",
		"Args": "0b"
	},
	{
		"LABEL": "0x506",
		"Type": "CLOSE_WINDOW",
		"SUBCMD": 1,
		"Args": "4f00"
	},
	{
		"LABEL": "0x50c",
		"Type": "IMAGELOAD",
		"SUBCMD": 0,
		"Args": "00005e04000000000000"
	},
	{
		"LABEL": "0x51a",
		"Type": "EQUN",
		"SUBCMD": 0,
		"Args": "3b1a0000"
	},
	{
		"LABEL": "0x522",
		"Type": "DRAW",
		"SUBCMD": 0,
		"Args": "1e00"
	},
	{
		"LABEL": "0x528",
		"Type": "WAIT",
		"SUBCMD": 0,
		"Args": ""
	},
	{
		"LABEL": "0x52c",
		"Type": "MESSAGE",
		"SUBCMD": 3,
		"SUBCMD2": 81,
		"MSGID": 21,
		"VOICEID": 10087,
		"NameJPN": "鴎",
		"JPN": "「やった」",
		"NameENG": "Kamome",
		"ENG": "\"Aw, yeah!\"",
		"Args": "0b"
	},
	{
		"LABEL": "0x54c",
		"Type": "MESSAGE",
		"SUBCMD": 3,
		"SUBCMD2": 83,
		"MSGID": 22,
		"VOICEID": 10088,
		"NameJPN": "鴎",
		"JPN": "「じゃあ、今日からがんばります」",
		"NameENG": "Kamome",
		"ENG": "\"Welp, I hope you like hard workers, 'cause I'm in it for the long haul!\"",
		"Args": "0b"
	},
	{
		"LABEL": "0x582",
		"Type": "CLOSE_WINDOW",
		"SUBCMD": 1,
		"Args": "5600"
	},
	{
		"LABEL": "0x588",
		"Type": "EQUN",
		"SUBCMD": 0,
		"Args": "3b1a0000"
	},
	{
		"LABEL": "0x590",
		"Type": "IMAGELOAD",
		"SUBCMD": 0,
		"Args": "0000b800000000000000"
	},
	{
		"LABEL": "0x59e",
		"Type": "INIT",
		"SUBCMD": 0,
		"Args": "01ff"
	},
	{
		"LABEL": "0x5a4",
		"Type": "DRAW",
		"SUBCMD": 0,
		"Args": "3c00"
	},
	{
		"LABEL": "0x5aa",
		"Type": "WAIT",
		"SUBCMD": 0,
		"Args": ""
	},
	{
		"LABEL": "0x5ae",
		"Type": "WAIT",
		"SUBCMD": 0,
		"Args": "3c00"
	},
	{
		"LABEL": "0x5b4",
		"Type": "CLOSE_WINDOW",
		"SUBCMD": 1,
		"Args": "5900"
	},
	{
		"LABEL": "0x5ba",
		"Type": "IMAGELOAD",
		"SUBCMD": 0,
		"Args": "00003d00000000000000"
	},
	{
		"LABEL": "0x5c8",
		"Type": "EQUN",
		"SUBCMD": 0,
		"Args": "3b1a0000"
	},
	{
		"LABEL": "0x5d0",
		"Type": "DRAW",
		"SUBCMD": 0,
		"Args": "3c00"
	},
	{
		"LABEL": "0x5d6",
		"Type": "WAIT",
		"SUBCMD": 0,
		"Args": ""
	},
	{
		"LABEL": "0x5da",
		"Type": "IMAGELOAD",
		"SUBCMD": 1,
		"Args": "5b0001000aac00008002b4009100"
	},
	{
		"LABEL": "0x5ec",
		"Type": "DRAW",
		"SUBCMD": 0,
		"Args": "0f00"
	},
	{
		"LABEL": "0x5f2",
		"Type": "MESSAGE",
		"SUBCMD": 3,
		"SUBCMD2": 93,
		"MSGID": 23,
		"VOICEID": 28250,
		"NameJPN": "うみ",
		"JPN": "「とてもはたらきものー」",
		"NameENG": "Umi",
		"ENG": "\"She works really hard!\"",
		"Args": "0b"
	},
	{
		"LABEL": "0x622",
		"Type": "MESSAGE",
		"SUBCMD": 3,
		"SUBCMD2": 95,
		"MSGID": 24,
		"JPN": "うみちゃんが感心していた。",
		"ENG": "Umi-chan seemed impressed.",
		"Args": "0b"
	},
	{
		"LABEL": "0x64c",
		"Type": "MESSAGE",
		"SUBCMD": 3,
		"SUBCMD2": 97,
		"MSGID": 25,
		"NameJPN": "羽依里",
		"JPN": "「外でも、やたらアクティブではあるな」",
		"NameENG": "Hairi",
		"ENG": "\"She's always got energy to burn.\"",
		"Args": "0b"
	},
	{
		"LABEL": "0x68c",
		"Type": "CLOSE_WINDOW",
		"SUBCMD": 1,
		"Args": "6400"
	},
	{
		"LABEL": "0x692",
		"Type": "INIT",
		"SUBCMD": 0,
		"Args": "0100"
	},
	{
		"LABEL": "0x698",
		"Type": "IMAGELOAD",
		"SUBCMD": 0,
		"Args": "00005c04000000000000"
	},
	{
		"LABEL": "0x6a6",
		"Type": "EQUN",
		"SUBCMD": 0,
		"Args": "3b1a0000"
	},
	{
		"LABEL": "0x6ae",
		"Type": "DRAW",
		"SUBCMD": 0,
		"Args": "3c00"
	},
	{
		"LABEL": "0x6b4",
		"Type": "WAIT",
		"SUBCMD": 0,
		"Args": ""
	},
	{
		"LABEL": "0x6b8",
		"Type": "MESSAGE",
		"SUBCMD": 3,
		"SUBCMD2": 102,
		"MSGID": 26,
		"VOICEID": 10090,
		"NameJPN": "鴎",
		"JPN": "「一通り終わったよ。他にやってもらいたいことある？」",
		"NameENG": "Kamome",
		"ENG": "\"That wraps up just about everything. Got anything else? Lay it on me.\"",
		"Args": "0b"
	},
	{
		"LABEL": "0x702",
		"Type": "MESSAGE",
		"SUBCMD": 3,
		"SUBCMD2": 104,
		"MSGID": 27,
		"VOICEID": 10091,
		"NameJPN": "鴎",
		"JPN": "「なんでも言って」",
		"NameENG": "Kamome",
		"ENG": "\"Anything at all!\"",
		"Args": "0b"
	},
	{
		"LABEL": "0x72a",
		"Type": "MESSAGE",
		"SUBCMD": 3,
		"SUBCMD2": 106,
		"MSGID": 28,
		"NameJPN": "羽依里",
		"JPN": "「なんでも、と言われても」",
		"NameENG": "Hairi",
		"ENG": "\"Anything?\"",
		"Args": "0b"
	},
	{
		"LABEL": "0x75e",
		"Type": "MESSAGE",
		"SUBCMD": 3,
		"SUBCMD2": 108,
		"MSGID": 29,
		"JPN": "何を頼もう。",
		"ENG": "What should I ask her to do?",
		"Args": "0b"
	},
	{
		"LABEL": "0x77a",
		"Type": "SELECT",
		"SUBCMD": 1,
		"Args": "700071174c01000000",
		"JPN": [
			"食事を手伝ってくれ",
			"掃除を手伝ってくれ",
			"着替えを手伝ってくれ"
		],
		"ENG": [
			"Help me cook",
			"Help me clean",
			"Help me change"
		],
		"Args2": "000004000000"
	},
	{
		"LABEL": "0x7d2",
		"Type": "IFN",
		"SUBCMD": 1,
		"Args": "7f00",
		"Equation": "(#6001==0)",
		"GOTO_LABEL": "0xf5a"
	},
	{
		"LABEL": "0x7e8",
		"Type": "MESSAGE",
		"SUBCMD": 3,
		"SUBCMD2": 133,
		"MSGID": 30,
		"NameJPN": "羽依里",
		"JPN": "「食事を」",
		"NameENG": "Hairi",
		"ENG": "\"How about some food?\"",
		"Args": "0b"
	},
	{
		"LABEL": "0x80c",
		"Type": "MESSAGE",
		"SUBCMD": 3,
		"SUBCMD2": 135,
		"MSGID": 31,
		"VOICEID": 10092,
		"NameJPN": "鴎",
		"JPN": "「任せて」",
		"NameENG": "Kamome",
		"ENG": "\"You got it!\"",
		"Args": "0b"
	},
	{
		"LABEL": "0x82c",
		"Type": "MESSAGE",
		"SUBCMD": 3,
		"SUBCMD2": 137,
		"MSGID": 32,
		"VOICEID": 10093,
		"NameJPN": "鴎",
		"JPN": "「今夜の夕食は作らせて貰っていいかな」",
		"NameENG": "Kamome",
		"ENG": "\"Mind if I make tonight's dinner?\"",
		"Args": "0b"
	},
	{
		"LABEL": "0x868",
		"Type": "MESSAGE",
		"SUBCMD": 3,
		"SUBCMD2": 139,
		"MSGID": 33,
		"VOICEID": 28251,
		"NameJPN": "うみ",
		"JPN": "「うん、いいよ」",
		"NameENG": "Umi",
		"ENG": "\"Okay, sure!\"",
		"Args": "0b"
	},
	{
		"LABEL": "0x890",
		"Type": "MESSAGE",
		"SUBCMD": 3,
		"SUBCMD2": 141,
		"MSGID": 34,
		"NameJPN": "羽依里",
		"JPN": "「冷蔵庫にあるものでなにか作れそうか？」",
		"NameENG": "Hairi",
		"ENG": "\"Is the stuff in the fridge all right?\"",
		"Args": "0b"
	},
	{
		"LABEL": "0x8d2",
		"Type": "MESSAGE",
		"SUBCMD": 3,
		"SUBCMD2": 143,
		"MSGID": 35,
		"VOICEID": 10097,
		"NameJPN": "鴎",
		"JPN": "「うん、出来ると思う」",
		"NameENG": "Kamome",
		"ENG": "\"Yep, should be just fine.\"",
		"Args": "0b"
	},
	{
		"LABEL": "0x8fe",
		"Type": "MESSAGE",
		"SUBCMD": 3,
		"SUBCMD2": 145,
		"MSGID": 36,
		"VOICEID": 10098,
		"NameJPN": "鴎",
		"JPN": "「鶏肉とトマトと……」",
		"NameENG": "Kamome",
		"ENG": "\"Chicken, tomatoes...\"",
		"Args": "0b"
	},
	{
		"LABEL": "0x92a",
		"Type": "MESSAGE",
		"SUBCMD": 3,
		"SUBCMD2": 147,
		"MSGID": 37,
		"VOICEID": 10099,
		"NameJPN": "鴎",
		"JPN": "「鶏肉のトマト煮込みとかどうかな」",
		"NameENG": "Kamome",
		"ENG": "\"How's chicken and tomato stew sound?\"",
		"Args": "0b"
	},
	{
		"LABEL": "0x962",
		"Type": "MESSAGE",
		"SUBCMD": 3,
		"SUBCMD2": 149,
		"MSGID": 38,
		"NameJPN": "羽依里",
		"JPN": "「お前は鶏肉食べられるのか」",
		"NameENG": "Hairi",
		"ENG": "\"You can eat poultry?\"",
		"Args": "0b"
	},
	{
		"LABEL": "0x998",
		"Type": "MESSAGE",
		"SUBCMD": 3,
		"SUBCMD2": 151,
		"MSGID": 39,
		"VOICEID": 10100,
		"NameJPN": "鴎",
		"JPN": "「……なんで」",
		"NameENG": "Kamome",
		"ENG": "\"...Why wouldn't I?\"",
		"Args": "0b"
	},
	{
		"LABEL": "0x9bc",
		"Type": "CLOSE_WINDOW",
		"SUBCMD": 1,
		"Args": "9b00"
	},
	{
		"LABEL": "0x9c2",
		"Type": "IMAGELOAD",
		"SUBCMD": 0,
		"Args": "00005d04000000000000"
	},
	{
		"LABEL": "0x9d0",
		"Type": "EQUN",
		"SUBCMD": 0,
		"Args": "3b1a0000"
	},
	{
		"LABEL": "0x9d8",
		"Type": "DRAW",
		"SUBCMD": 0,
		"Args": "1e00"
	},
	{
		"LABEL": "0x9de",
		"Type": "WAIT",
		"SUBCMD": 0,
		"Args": ""
	},
	{
		"LABEL": "0x9e2",
		"Type": "MESSAGE",
		"SUBCMD": 3,
		"SUBCMD2": 157,
		"MSGID": 40,
		"VOICEID": 10101,
		"NameJPN": "鴎",
		"JPN": "「あのねぇ、こんな名前だけど、鳥さんに仲間意識を持ってるわけじゃないよ」",
		"NameENG": "Kamome",
		"ENG": "\"Listen here, buster. I know what you're getting at with the whole 'gull' thing, but that doesn't mean I'm flighty about my tastes.\"",
		"Args": "0b"
	},
	{
		"LABEL": "0xa40",
		"Type": "MESSAGE",
		"SUBCMD": 3,
		"SUBCMD2": 159,
		"MSGID": 41,
		"VOICEID": 10102,
		"NameJPN": "鴎",
		"JPN": "「そんなこといったら羽依里だって、手羽先とか食べられないじゃない」",
		"NameENG": "Kamome",
		"ENG": "\"Or what, are chicken wings off your menu? 'Hairi' starts with the kanji for wing, doesn't it?\"",
		"Args": "0b"
	},
	{
		"LABEL": "0xa98",
		"Type": "MESSAGE",
		"SUBCMD": 3,
		"SUBCMD2": 161,
		"MSGID": 42,
		"VOICEID": 28252,
		"NameJPN": "うみ",
		"JPN": "「はいり……てばさき……？」",
		"NameENG": "Umi",
		"ENG": "\"Hairi... Chicken wings...?\"",
		"Args": "0b"
	},
	{
		"LABEL": "0xacc",
		"Type": "MESSAGE",
		"SUBCMD": 3,
		"SUBCMD2": 163,
		"MSGID": 43,
		"VOICEID": 28253,
		"NameJPN": "うみ",
		"JPN": "「うみゅ？」",
		"NameENG": "Umi",
		"ENG": "\"Umyu?\"",
		"Args": "0b"
	},
	{
		"LABEL": "0xaf0",
		"Type": "MESSAGE",
		"SUBCMD": 3,
		"SUBCMD2": 165,
		"MSGID": 44,
		"NameJPN": "羽依里",
		"JPN": "「うん、よくわかんないな」",
		"NameENG": "Hairi",
		"ENG": "\"Yeah, that was a stretch.\"",
		"Args": "0b"
	},
	{
		"LABEL": "0xb24",
		"Type": "MESSAGE",
		"SUBCMD": 3,
		"SUBCMD2": 167,
		"MSGID": 45,
		"JPN": "せめて文字数くらい合わせて欲しい。",
		"ENG": "It's gonna take more than a single kanji reference to achieve my level of humor.",
		"Args": "0b"
	},
	{
		"LABEL": "0xb56",
		"Type": "CLOSE_WINDOW",
		"SUBCMD": 1,
		"Args": "a900"
	},
	{
		"LABEL": "0xb5c",
		"Type": "IMAGELOAD",
		"SUBCMD": 0,
		"Args": "0208b800100000000000"
	},
	{
		"LABEL": "0xb6a",
		"Type": "EQUN",
		"SUBCMD": 0,
		"Args": "3b1a0000"
	},
	{
		"LABEL": "0xb72",
		"Type": "INIT",
		"SUBCMD": 0,
		"Args": "01ff"
	},
	{
		"LABEL": "0xb78",
		"Type": "DRAW",
		"SUBCMD": 0,
		"Args": "3c00"
	},
	{
		"LABEL": "0xb7e",
		"Type": "WAIT",
		"SUBCMD": 0,
		"Args": "3c00"
	},
	{
		"LABEL": "0xb84",
		"Type": "IMAGELOAD",
		"SUBCMD": 0,
		"Args": "0000b800000000000000"
	},
	{
		"LABEL": "0xb92",
		"Type": "INIT",
		"SUBCMD": 0,
		"Args": "0208"
	},
	{
		"LABEL": "0xb98",
		"Type": "DRAW",
		"SUBCMD": 0,
		"Args": ""
	},
	{
		"LABEL": "0xb9c",
		"Type": "CLOSE_WINDOW",
		"SUBCMD": 1,
		"Args": "ab00"
	},
	{
		"LABEL": "0xba2",
		"Type": "IMAGELOAD",
		"SUBCMD": 0,
		"Args": "00004100000000000000"
	},
	{
		"LABEL": "0xbb0",
		"Type": "EQUN",
		"SUBCMD": 0,
		"Args": "3b1a0000"
	},
	{
		"LABEL": "0xbb8",
		"Type": "DRAW",
		"SUBCMD": 0,
		"Args": "3c00"
	},
	{
		"LABEL": "0xbbe",
		"Type": "WAIT",
		"SUBCMD": 0,
		"Args": ""
	},
	{
		"LABEL": "0xbc2",
		"Type": "IMAGELOAD",
		"SUBCMD": 1,
		"Args": "ac0001006a6c00008002b400dd00"
	},
	{
		"LABEL": "0xbd4",
		"Type": "DRAW",
		"SUBCMD": 0,
		"Args": "0f00"
	},
	{
		"LABEL": "0xbda",
		"Type": "MESSAGE",
		"SUBCMD": 3,
		"SUBCMD2": 174,
		"MSGID": 46,
		"VOICEID": 10105,
		"NameJPN": "鴎",
		"JPN": "「じゃあ早速作っちゃうね」",
		"NameENG": "Kamome",
		"ENG": "\"Let's get right to it.\"",
		"Args": "0b"
	},
	{
		"LABEL": "0xc0a",
		"Type": "IMAGEUPDATE",
		"SUBCMD": 1,
		"Args": "b00001008c6c"
	},
	{
		"LABEL": "0xc14",
		"Type": "DRAW",
		"SUBCMD": 0,
		"Args": "0f00"
	},
	{
		"LABEL": "0xc1a",
		"Type": "MESSAGE",
		"SUBCMD": 3,
		"SUBCMD2": 178,
		"MSGID": 47,
		"VOICEID": 10106,
		"NameJPN": "鴎",
		"JPN": "「鶏肉って包丁で切りづらいよね」",
		"NameENG": "Kamome",
		"ENG": "\"Man, chicken's kinda hard to cut through. Am I right?\"",
		"Args": "0b"
	},
	{
		"LABEL": "0xc50",
		"Type": "IMAGEUPDATE",
		"SUBCMD": 1,
		"Args": "b40001006a6c"
	},
	{
		"LABEL": "0xc5a",
		"Type": "DRAW",
		"SUBCMD": 0,
		"Args": "0f00"
	},
	{
		"LABEL": "0xc60",
		"Type": "MESSAGE",
		"SUBCMD": 3,
		"SUBCMD2": 182,
		"MSGID": 48,
		"VOICEID": 10107,
		"NameJPN": "鴎",
		"JPN": "「よいしょ」",
		"NameENG": "Kamome",
		"ENG": "\"Ngh...\"",
		"Args": "0b"
	},
	{
		"LABEL": "0xc82",
		"Type": "QUAKE",
		"SUBCMD": 1,
		"Args": "b800ff0001060000520001010052"
	},
	{
		"LABEL": "0xc94",
		"Type": "QUAKE",
		"SUBCMD": 0,
		"Args": "ff0901060000520001010000"
	},
	{
		"LABEL": "0xca4",
		"Type": "MESSAGE",
		"SUBCMD": 3,
		"SUBCMD2": 186,
		"MSGID": 49,
		"NameJPN": "羽依里",
		"JPN": "「ぐあああ」",
		"NameENG": "Hairi",
		"ENG": "\"Guaaaaghhh!\"",
		"Args": "0b"
	},
	{
		"LABEL": "0xcca",
		"Type": "IMAGEUPDATE",
		"SUBCMD": 1,
		"Args": "bc000100726c"
	},
	{
		"LABEL": "0xcd4",
		"Type": "DRAW",
		"SUBCMD": 0,
		"Args": "0f00"
	},
	{
		"LABEL": "0xcda",
		"Type": "MESSAGE",
		"SUBCMD": 3,
		"SUBCMD2": 190,
		"MSGID": 50,
		"VOICEID": 10108,
		"NameJPN": "鴎",
		"JPN": "「……よいしょ」",
		"NameENG": "Kamome",
		"ENG": "\"O...kay.\"",
		"Args": "0b"
	},
	{
		"LABEL": "0xd00",
		"Type": "MESSAGE",
		"SUBCMD": 3,
		"SUBCMD2": 192,
		"MSGID": 51,
		"NameJPN": "羽依里",
		"JPN": "「裏切ったな鴎。同じ鳥でありながらこの仕打ち」",
		"NameENG": "Hairi",
		"ENG": "\"Kamome, you would betray your fallen, feathered friends?\"",
		"Args": "0b"
	},
	{
		"LABEL": "0xd48",
		"Type": "QUAKE",
		"SUBCMD": 1,
		"Args": "c200ff0001060000520001010052"
	},
	{
		"LABEL": "0xd5a",
		"Type": "QUAKE",
		"SUBCMD": 0,
		"Args": "ff0901060000520001010000"
	},
	{
		"LABEL": "0xd6a",
		"Type": "MESSAGE",
		"SUBCMD": 3,
		"SUBCMD2": 196,
		"MSGID": 52,
		"NameJPN": "羽依里",
		"JPN": "「ぎゃあああ」",
		"NameENG": "Hairi",
		"ENG": "\"Gyaaaaahhh!\"",
		"Args": "0b"
	},
	{
		"LABEL": "0xd92",
		"Type": "IMAGEUPDATE",
		"SUBCMD": 1,
		"Args": "c6000100826c"
	},
	{
		"LABEL": "0xd9c",
		"Type": "DRAW",
		"SUBCMD": 0,
		"Args": "0f00"
	},
	{
		"LABEL": "0xda2",
		"Type": "MESSAGE",
		"SUBCMD": 3,
		"SUBCMD2": 200,
		"MSGID": 53,
		"VOICEID": 10109,
		"NameJPN": "鴎",
		"JPN": "「やめてくれますか」",
		"NameENG": "Kamome",
		"ENG": "\"Could you please stop?\"",
		"Args": "0b"
	},
	{
		"LABEL": "0xdcc",
		"Type": "MESSAGE",
		"SUBCMD": 3,
		"SUBCMD2": 202,
		"MSGID": 54,
		"NameJPN": "羽依里",
		"JPN": "「なんか暇なんだ」",
		"NameENG": "Hairi",
		"ENG": "\"What else am I supposed to do?\"",
		"Args": "0b"
	},
	{
		"LABEL": "0xdf8",
		"Type": "IMAGEUPDATE",
		"SUBCMD": 1,
		"Args": "cc000100846c"
	},
	{
		"LABEL": "0xe02",
		"Type": "DRAW",
		"SUBCMD": 0,
		"Args": "0f00"
	},
	{
		"LABEL": "0xe08",
		"Type": "MESSAGE",
		"SUBCMD": 3,
		"SUBCMD2": 206,
		"MSGID": 55,
		"VOICEID": 10110,
		"NameJPN": "鴎",
		"JPN": "「この人いつもこうなの」",
		"NameENG": "Kamome",
		"ENG": "\"Is this guy always like this?\"",
		"Args": "0b"
	},
	{
		"LABEL": "0xe36",
		"Type": "IMAGELOAD",
		"SUBCMD": 1,
		"Args": "d000060076ad09006b00dcfe"
	},
	{
		"LABEL": "0xe46",
		"Type": "MESSAGE",
		"SUBCMD": 3,
		"SUBCMD2": 210,
		"MSGID": 56,
		"VOICEID": 28254,
		"NameJPN": "うみ",
		"JPN": "「ううん、きょうはとくべつみたいー」",
		"NameENG": "Umi",
		"ENG": "\"Nope. Today's special.\"",
		"Args": "0b"
	},
	{
		"LABEL": "0xe82",
		"Type": "IMAGELOAD",
		"SUBCMD": 1,
		"Args": "d400060094ad09006b00dcfe"
	},
	{
		"LABEL": "0xe92",
		"Type": "MESSAGE",
		"SUBCMD": 3,
		"SUBCMD2": 214,
		"MSGID": 57,
		"VOICEID": 28255,
		"NameJPN": "うみ",
		"JPN": "「かもめさん、いるから？」",
		"NameENG": "Umi",
		"ENG": "\"Maybe because you're here?\"",
		"Args": "0b"
	},
	{
		"LABEL": "0xec4",
		"Type": "IMAGEUPDATE",
		"SUBCMD": 1,
		"Args": "d8000100746c"
	},
	{
		"LABEL": "0xece",
		"Type": "DRAW",
		"SUBCMD": 0,
		"Args": "0f00"
	},
	{
		"LABEL": "0xed4",
		"Type": "MESSAGE",
		"SUBCMD": 3,
		"SUBCMD2": 218,
		"MSGID": 58,
		"NameJPN": "羽依里",
		"JPN": "「ち、違う」",
		"NameENG": "Hairi",
		"ENG": "\"Th-That's not...!\"",
		"Args": "0b"
	},
	{
		"LABEL": "0xefa",
		"Type": "IMAGEUPDATE",
		"SUBCMD": 1,
		"Args": "dc0001006c6c"
	},
	{
		"LABEL": "0xf04",
		"Type": "DRAW",
		"SUBCMD": 0,
		"Args": "0f00"
	},
	{
		"LABEL": "0xf0a",
		"Type": "MESSAGE",
		"SUBCMD": 3,
		"SUBCMD2": 222,
		"MSGID": 59,
		"VOICEID": 10112,
		"NameJPN": "鴎",
		"JPN": "「ま」",
		"NameENG": "Kamome",
		"ENG": "\"Golly.\"",
		"Args": "0b"
	},
	{
		"LABEL": "0xf26",
		"Type": "MESSAGE",
		"SUBCMD": 3,
		"SUBCMD2": 224,
		"MSGID": 60,
		"NameJPN": "羽依里",
		"JPN": "「ま、じゃない」",
		"NameENG": "Hairi",
		"ENG": "\"Take your 'golly' somewhere else.\"",
		"Args": "0b"
	},
	{
		"LABEL": "0xf50",
		"Type": "GOTO",
		"SUBCMD": 1,
		"Args": "e400",
		"GOTO_LABEL": "0x2410"
	},
	{
		"LABEL": "0xf5a",
		"Type": "IFN",
		"SUBCMD": 1,
		"Args": "e700",
		"Equation": "(#6001==1)",
		"GOTO_LABEL": "0x1890"
	},
	{
		"LABEL": "0xf70",
		"Type": "MESSAGE",
		"SUBCMD": 3,
		"SUBCMD2": 233,
		"MSGID": 61,
		"NameJPN": "羽依里",
		"JPN": "「じゃあ掃除を頼む」",
		"NameENG": "Hairi",
		"ENG": "\"Could you help clean?\"",
		"Args": "0b"
	},
	{
		"LABEL": "0xf9e",
		"Type": "MESSAGE",
		"SUBCMD": 3,
		"SUBCMD2": 235,
		"MSGID": 62,
		"VOICEID": 10113,
		"NameJPN": "鴎",
		"JPN": "「そらきた」",
		"NameENG": "Kamome",
		"ENG": "\"Ah-ha! There it is!\"",
		"Args": "0b"
	},
	{
		"LABEL": "0xfc0",
		"Type": "MESSAGE",
		"SUBCMD": 3,
		"SUBCMD2": 237,
		"MSGID": 63,
		"VOICEID": 10114,
		"NameJPN": "鴎",
		"JPN": "「男の子は片付けできないからねぇ」",
		"NameENG": "Kamome",
		"ENG": "\"I know how you boys work. Wouldn't know 'tidy' if it hit you in the face.\"",
		"Args": "0b"
	},
	{
		"LABEL": "0xff8",
		"Type": "MESSAGE",
		"SUBCMD": 3,
		"SUBCMD2": 239,
		"MSGID": 64,
		"VOICEID": 10115,
		"NameJPN": "鴎",
		"JPN": "「掃除、掃除と……」",
		"NameENG": "Kamome",
		"ENG": "\"Cleaning, cleaning～!\"",
		"Args": "0b"
	},
	{
		"LABEL": "0x1022",
		"Type": "CLOSE_WINDOW",
		"SUBCMD": 1,
		"Args": "f100"
	},
	{
		"LABEL": "0x1028",
		"Type": "IMAGELOAD",
		"SUBCMD": 0,
		"Args": "0208b800100000000000"
	},
	{
		"LABEL": "0x1036",
		"Type": "EQUN",
		"SUBCMD": 0,
		"Args": "3b1a0000"
	},
	{
		"LABEL": "0x103e",
		"Type": "INIT",
		"SUBCMD": 0,
		"Args": "01ff"
	},
	{
		"LABEL": "0x1044",
		"Type": "DRAW",
		"SUBCMD": 0,
		"Args": "3c00"
	},
	{
		"LABEL": "0x104a",
		"Type": "WAIT",
		"SUBCMD": 0,
		"Args": "3c00"
	},
	{
		"LABEL": "0x1050",
		"Type": "IMAGELOAD",
		"SUBCMD": 0,
		"Args": "0000b800000000000000"
	},
	{
		"LABEL": "0x105e",
		"Type": "INIT",
		"SUBCMD": 0,
		"Args": "0208"
	},
	{
		"LABEL": "0x1064",
		"Type": "DRAW",
		"SUBCMD": 0,
		"Args": ""
	},
	{
		"LABEL": "0x1068",
		"Type": "MESSAGE",
		"SUBCMD": 3,
		"SUBCMD2": 243,
		"MSGID": 65,
		"JPN": "……",
		"ENG": "......",
		"Args": "0b"
	},
	{
		"LABEL": "0x107c",
		"Type": "CLOSE_WINDOW",
		"SUBCMD": 1,
		"Args": "f500"
	},
	{
		"LABEL": "0x1082",
		"Type": "IMAGELOAD",
		"SUBCMD": 0,
		"Args": "00005c04000000000000"
	},
	{
		"LABEL": "0x1090",
		"Type": "EQUN",
		"SUBCMD": 0,
		"Args": "3b1a0000"
	},
	{
		"LABEL": "0x1098",
		"Type": "DRAW",
		"SUBCMD": 0,
		"Args": "3c00"
	},
	{
		"LABEL": "0x109e",
		"Type": "WAIT",
		"SUBCMD": 0,
		"Args": ""
	},
	{
		"LABEL": "0x10a2",
		"Type": "MESSAGE",
		"SUBCMD": 3,
		"SUBCMD2": 247,
		"MSGID": 66,
		"VOICEID": 10116,
		"NameJPN": "鴎",
		"JPN": "「けっこう綺麗だよ」",
		"NameENG": "Kamome",
		"ENG": "\"What the heck. It's clean.\"",
		"Args": "0b"
	},
	{
		"LABEL": "0x10cc",
		"Type": "MESSAGE",
		"SUBCMD": 3,
		"SUBCMD2": 249,
		"MSGID": 67,
		"NameJPN": "羽依里",
		"JPN": "「うみちゃんが丁寧にしてるからね」",
		"NameENG": "Hairi",
		"ENG": "\"Umi-chan's on top of that stuff.\"",
		"Args": "0b"
	},
	{
		"LABEL": "0x1108",
		"Type": "MESSAGE",
		"SUBCMD": 3,
		"SUBCMD2": 251,
		"MSGID": 68,
		"VOICEID": 10117,
		"NameJPN": "鴎",
		"JPN": "「どこ掃除したらいいかな」",
		"NameENG": "Kamome",
		"ENG": "\"Where should I clean then?\"",
		"Args": "0b"
	},
	{
		"LABEL": "0x1138",
		"Type": "MESSAGE",
		"SUBCMD": 3,
		"SUBCMD2": 253,
		"MSGID": 69,
		"VOICEID": 28256,
		"NameJPN": "うみ",
		"JPN": "「じゃー、おにーちゃんのへやー」",
		"NameENG": "Umi",
		"ENG": "\"Onii-chan's room!\"",
		"Args": "0b"
	},
	{
		"LABEL": "0x1170",
		"Type": "MESSAGE",
		"SUBCMD": 3,
		"SUBCMD2": 255,
		"MSGID": 70,
		"NameJPN": "羽依里",
		"JPN": "「え？」",
		"NameENG": "Hairi",
		"ENG": "\"Huh?\"",
		"Args": "0b"
	},
	{
		"LABEL": "0x1192",
		"Type": "MESSAGE",
		"SUBCMD": 3,
		"SUBCMD2": 257,
		"MSGID": 71,
		"VOICEID": 10119,
		"NameJPN": "鴎",
		"JPN": "「じゃあ、そこ行ってみよう」",
		"NameENG": "Kamome",
		"ENG": "\"Let's give it a look!\"",
		"Args": "0b"
	},
	{
		"LABEL": "0x11c4",
		"Type": "MESSAGE",
		"SUBCMD": 3,
		"SUBCMD2": 259,
		"MSGID": 72,
		"NameJPN": "羽依里",
		"JPN": "「ええ……」",
		"NameENG": "Hairi",
		"ENG": "\"Uh...\"",
		"Args": "0b"
	},
	{
		"LABEL": "0x11ea",
		"Type": "CLOSE_WINDOW",
		"SUBCMD": 1,
		"Args": "0501"
	},
	{
		"LABEL": "0x11f0",
		"Type": "IMAGELOAD",
		"SUBCMD": 0,
		"Args": "0208b800100000000000"
	},
	{
		"LABEL": "0x11fe",
		"Type": "EQUN",
		"SUBCMD": 0,
		"Args": "3b1a0000"
	},
	{
		"LABEL": "0x1206",
		"Type": "INIT",
		"SUBCMD": 0,
		"Args": "01ff"
	},
	{
		"LABEL": "0x120c",
		"Type": "DRAW",
		"SUBCMD": 0,
		"Args": "3c0000001227"
	},
	{
		"LABEL": "0x1216",
		"Type": "WAIT",
		"SUBCMD": 0,
		"Args": "3c00"
	},
	{
		"LABEL": "0x121c",
		"Type": "IMAGELOAD",
		"SUBCMD": 0,
		"Args": "0000b800000000000000"
	},
	{
		"LABEL": "0x122a",
		"Type": "INIT",
		"SUBCMD": 0,
		"Args": "0208"
	},
	{
		"LABEL": "0x1230",
		"Type": "DRAW",
		"SUBCMD": 0,
		"Args": ""
	},
	{
		"LABEL": "0x1234",
		"Type": "IMAGELOAD",
		"SUBCMD": 1,
		"Args": "080100004400000000000000"
	},
	{
		"LABEL": "0x1244",
		"Type": "SCALE",
		"SUBCMD": 0,
		"Args": "00000000003e003e"
	},
	{
		"LABEL": "0x1250",
		"Type": "EVSCROLL",
		"SUBCMD": 0,
		"Args": "000000"
	},
	{
		"LABEL": "0x1258",
		"Type": "MOVE",
		"SUBCMD": 0,
		"Args": "000000000000004cff"
	},
	{
		"LABEL": "0x1266",
		"Type": "MOVE",
		"SUBCMD": 0,
		"Args": "00000a340880fd4cff"
	},
	{
		"LABEL": "0x1274",
		"Type": "EQUN",
		"SUBCMD": 0,
		"Args": "3b1a0000"
	},
	{
		"LABEL": "0x127c",
		"Type": "DRAW",
		"SUBCMD": 0,
		"Args": "3c0000001227"
	},
	{
		"LABEL": "0x1286",
		"Type": "WAIT",
		"SUBCMD": 1,
		"Args": "09013c00"
	},
	{
		"LABEL": "0x128e",
		"Type": "IMAGELOAD",
		"SUBCMD": 1,
		"Args": "0d010600696c0900650061ff"
	},
	{
		"LABEL": "0x129e",
		"Type": "MESSAGE",
		"SUBCMD": 3,
		"SUBCMD2": 271,
		"MSGID": 73,
		"VOICEID": 10120,
		"NameJPN": "鴎",
		"JPN": "「さてとどこから手をつけようか」",
		"NameENG": "Kamome",
		"ENG": "\"Now, where to start.\"",
		"Args": "0b"
	},
	{
		"LABEL": "0x12d4",
		"Type": "IMAGELOAD",
		"SUBCMD": 1,
		"Args": "11010600856c0900650061ff"
	},
	{
		"LABEL": "0x12e4",
		"Type": "MESSAGE",
		"SUBCMD": 3,
		"SUBCMD2": 275,
		"MSGID": 74,
		"VOICEID": 10121,
		"NameJPN": "鴎",
		"JPN": "「ふむ」",
		"NameENG": "Kamome",
		"ENG": "\"Hm.\"",
		"Args": "0b"
	},
	{
		"LABEL": "0x1302",
		"Type": "MESSAGE",
		"SUBCMD": 3,
		"SUBCMD2": 277,
		"MSGID": 75,
		"JPN": "珍しそうに俺の部屋を見回す。",
		"ENG": "She looked around my room curiously.",
		"Args": "0b"
	},
	{
		"LABEL": "0x132e",
		"Type": "IMAGELOAD",
		"SUBCMD": 1,
		"Args": "17010600716c0900650061ff"
	},
	{
		"LABEL": "0x133e",
		"Type": "MESSAGE",
		"SUBCMD": 3,
		"SUBCMD2": 281,
		"MSGID": 76,
		"VOICEID": 10122,
		"NameJPN": "鴎",
		"JPN": "「男の子の本棚には秘密が隠されているという」",
		"NameENG": "Kamome",
		"ENG": "\"They say that within a man's bookcase dwells many a secret.\"",
		"Args": "0b"
	},
	{
		"LABEL": "0x1380",
		"Type": "MESSAGE",
		"SUBCMD": 3,
		"SUBCMD2": 284,
		"MSGID": 77,
		"NameJPN": "羽依里",
		"JPN": "「どこに興味がわいてるんだ」",
		"NameENG": "Hairi",
		"ENG": "\"Oh, do they now?\"",
		"Args": "0b"
	},
	{
		"LABEL": "0x13b6",
		"Type": "CLOSE_WINDOW",
		"SUBCMD": 1,
		"Args": "1e01"
	},
	{
		"LABEL": "0x13bc",
		"Type": "IMAGELOAD",
		"SUBCMD": 0,
		"Args": "00004400000000000000"
	},
	{
		"LABEL": "0x13ca",
		"Type": "EQUN",
		"SUBCMD": 0,
		"Args": "3b1a0000"
	},
	{
		"LABEL": "0x13d2",
		"Type": "DRAW",
		"SUBCMD": 0,
		"Args": "3c00"
	},
	{
		"LABEL": "0x13d8",
		"Type": "WAIT",
		"SUBCMD": 0,
		"Args": ""
	},
	{
		"LABEL": "0x13dc",
		"Type": "IMAGELOAD",
		"SUBCMD": 1,
		"Args": "1f0101006a6c00008002b400dd00"
	},
	{
		"LABEL": "0x13ee",
		"Type": "DRAW",
		"SUBCMD": 0,
		"Args": "0f00"
	},
	{
		"LABEL": "0x13f4",
		"Type": "MESSAGE",
		"SUBCMD": 3,
		"SUBCMD2": 289,
		"MSGID": 78,
		"VOICEID": 10123,
		"NameJPN": "鴎",
		"JPN": "「……なになに」",
		"NameENG": "Kamome",
		"ENG": "\"What do we have here?\"",
		"Args": "0b"
	},
	{
		"LABEL": "0x141a",
		"Type": "IMAGEUPDATE",
		"SUBCMD": 1,
		"Args": "23010100866c"
	},
	{
		"LABEL": "0x1424",
		"Type": "DRAW",
		"SUBCMD": 0,
		"Args": "0f00"
	},
	{
		"LABEL": "0x142a",
		"Type": "MESSAGE",
		"SUBCMD": 3,
		"SUBCMD2": 293,
		"MSGID": 79,
		"VOICEID": 10124,
		"NameJPN": "鴎",
		"JPN": "「『世界怪奇事件集』『暗黒神の末裔』」",
		"NameENG": "Kamome",
		"ENG": "\"'Paranormal Mysteries of the World'... 'The Descendants of the Dark God'...\"",
		"Args": "0b"
	},
	{
		"LABEL": "0x1466",
		"Type": "IMAGEUPDATE",
		"SUBCMD": 1,
		"Args": "270101007c6c"
	},
	{
		"LABEL": "0x1470",
		"Type": "DRAW",
		"SUBCMD": 0,
		"Args": "0f00"
	},
	{
		"LABEL": "0x1476",
		"Type": "MESSAGE",
		"SUBCMD": 3,
		"SUBCMD2": 297,
		"MSGID": 80,
		"VOICEID": 10125,
		"NameJPN": "鴎",
		"JPN": "「うわ」",
		"NameENG": "Kamome",
		"ENG": "\"Wow, okay.\"",
		"Args": "0b"
	},
	{
		"LABEL": "0x1494",
		"Type": "IMAGEUPDATE",
		"SUBCMD": 1,
		"Args": "2b010100826c"
	},
	{
		"LABEL": "0x149e",
		"Type": "DRAW",
		"SUBCMD": 0,
		"Args": "0f00"
	},
	{
		"LABEL": "0x14a4",
		"Type": "MESSAGE",
		"SUBCMD": 3,
		"SUBCMD2": 301,
		"MSGID": 81,
		"VOICEID": 10126,
		"NameJPN": "鴎",
		"JPN": "「ラインナップがこわい」",
		"NameENG": "Kamome",
		"ENG": "\"Every one of these sounds scary.\"",
		"Args": "0b"
	},
	{
		"LABEL": "0x14d2",
		"Type": "MESSAGE",
		"SUBCMD": 3,
		"SUBCMD2": 303,
		"MSGID": 82,
		"NameJPN": "羽依里",
		"JPN": "「お前だって冒険小説とか好きだろう」",
		"NameENG": "Hairi",
		"ENG": "\"Aren't you into adventure stories?\"",
		"Args": "0b"
	},
	{
		"LABEL": "0x1510",
		"Type": "IMAGEUPDATE",
		"SUBCMD": 1,
		"Args": "31010100866c"
	},
	{
		"LABEL": "0x151a",
		"Type": "DRAW",
		"SUBCMD": 0,
		"Args": "0f00"
	},
	{
		"LABEL": "0x1520",
		"Type": "MESSAGE",
		"SUBCMD": 3,
		"SUBCMD2": 307,
		"MSGID": 83,
		"VOICEID": 10127,
		"NameJPN": "鴎",
		"JPN": "「好きだけど？」",
		"NameENG": "Kamome",
		"ENG": "\"Sure, but why do you ask?\"",
		"Args": "0b"
	},
	{
		"LABEL": "0x1546",
		"Type": "MESSAGE",
		"SUBCMD": 3,
		"SUBCMD2": 309,
		"MSGID": 84,
		"NameJPN": "羽依里",
		"JPN": "「未知への好奇心という意味では、似たようなものだ」",
		"NameENG": "Hairi",
		"ENG": "\"They're both all about that curiosity for the unknown. Our tastes aren't so different.\"",
		"Args": "0b"
	},
	{
		"LABEL": "0x1592",
		"Type": "IMAGEUPDATE",
		"SUBCMD": 1,
		"Args": "37010100726c"
	},
	{
		"LABEL": "0x159c",
		"Type": "DRAW",
		"SUBCMD": 0,
		"Args": "0f00"
	},
	{
		"LABEL": "0x15a2",
		"Type": "MESSAGE",
		"SUBCMD": 3,
		"SUBCMD2": 313,
		"MSGID": 85,
		"VOICEID": 10128,
		"NameJPN": "鴎",
		"JPN": "「似て非なるものだと思う」",
		"NameENG": "Kamome",
		"ENG": "\"Maybe to you.\"",
		"Args": "0b"
	},
	{
		"LABEL": "0x15d2",
		"Type": "MESSAGE",
		"SUBCMD": 3,
		"SUBCMD2": 315,
		"MSGID": 86,
		"NameJPN": "羽依里",
		"JPN": "「お前のスーツケースの中も、けっこうぐろいのを期待してる」",
		"NameENG": "Hairi",
		"ENG": "\"I'm looking forward to finally seeing whatever gruesome horror you're keeping in your suitcase as well.\"",
		"Args": "0b"
	},
	{
		"LABEL": "0x1626",
		"Type": "IMAGEUPDATE",
		"SUBCMD": 1,
		"Args": "3d0101008e6c"
	},
	{
		"LABEL": "0x1630",
		"Type": "DRAW",
		"SUBCMD": 0,
		"Args": "0f00"
	},
	{
		"LABEL": "0x1636",
		"Type": "MESSAGE",
		"SUBCMD": 3,
		"SUBCMD2": 319,
		"MSGID": 87,
		"VOICEID": 10129,
		"NameJPN": "鴎",
		"JPN": "「ひどい！」",
		"NameENG": "Kamome",
		"ENG": "\"You are just the worst!\"",
		"Args": "0b"
	},
	{
		"LABEL": "0x1658",
		"Type": "MESSAGE",
		"SUBCMD": 3,
		"SUBCMD2": 323,
		"MSGID": 88,
		"VOICEID": 10130,
		"NameJPN": "鴎",
		"JPN": "「ぐろいわけないよ」",
		"NameENG": "Kamome",
		"ENG": "\"Sorry, but you're gonna be disappointed!\"",
		"Args": "0b"
	},
	{
		"LABEL": "0x1682",
		"Type": "MESSAGE",
		"SUBCMD": 3,
		"SUBCMD2": 325,
		"MSGID": 89,
		"NameJPN": "羽依里",
		"JPN": "「そうなのか。全然中を見せようとしないから、ぐろいのかなって」",
		"NameENG": "Hairi",
		"ENG": "\"Am I? You've never let me see, so I got my hopes$dup.\"",
		"Args": "0b"
	},
	{
		"LABEL": "0x16da",
		"Type": "IMAGEUPDATE",
		"SUBCMD": 1,
		"Args": "470101007c6c"
	},
	{
		"LABEL": "0x16e4",
		"Type": "DRAW",
		"SUBCMD": 0,
		"Args": "0f00"
	},
	{
		"LABEL": "0x16ea",
		"Type": "MESSAGE",
		"SUBCMD": 3,
		"SUBCMD2": 329,
		"MSGID": 90,
		"VOICEID": 10131,
		"NameJPN": "鴎",
		"JPN": "「見せないとぐろいの!?　どういう推理??」",
		"NameENG": "Kamome",
		"ENG": "\"It's a gruesome horror because I won't show you!? How do you jump to that conclusion!?\"",
		"Args": "0b"
	},
	{
		"LABEL": "0x172c",
		"Type": "IMAGEUPDATE",
		"SUBCMD": 1,
		"Args": "4b010100726c"
	},
	{
		"LABEL": "0x1736",
		"Type": "DRAW",
		"SUBCMD": 0,
		"Args": "0f00"
	},
	{
		"LABEL": "0x173c",
		"Type": "MESSAGE",
		"SUBCMD": 3,
		"SUBCMD2": 333,
		"MSGID": 91,
		"VOICEID": 10132,
		"NameJPN": "鴎",
		"JPN": "「なんならここで見せてあげようか」",
		"NameENG": "Kamome",
		"ENG": "\"Fine, I'll just have to prove it. Here and now.\"",
		"Args": "0b"
	},
	{
		"LABEL": "0x1774",
		"Type": "MESSAGE",
		"SUBCMD": 3,
		"SUBCMD2": 335,
		"MSGID": 92,
		"NameJPN": "羽依里",
		"JPN": "「ほんとか」",
		"NameENG": "Hairi",
		"ENG": "\"Really?\"",
		"Args": "0b"
	},
	{
		"LABEL": "0x179a",
		"Type": "IMAGEUPDATE",
		"SUBCMD": 1,
		"Args": "51010100746c"
	},
	{
		"LABEL": "0x17a4",
		"Type": "DRAW",
		"SUBCMD": 0,
		"Args": "0f00"
	},
	{
		"LABEL": "0x17aa",
		"Type": "MESSAGE",
		"SUBCMD": 3,
		"SUBCMD2": 339,
		"MSGID": 93,
		"VOICEID": 10133,
		"NameJPN": "鴎",
		"JPN": "「……は」",
		"NameENG": "Kamome",
		"ENG": "\"...Hah!\"",
		"Args": "0b"
	},
	{
		"LABEL": "0x17ca",
		"Type": "IMAGEUPDATE",
		"SUBCMD": 1,
		"Args": "55010100826c"
	},
	{
		"LABEL": "0x17d4",
		"Type": "DRAW",
		"SUBCMD": 0,
		"Args": "0f00"
	},
	{
		"LABEL": "0x17da",
		"Type": "MESSAGE",
		"SUBCMD": 3,
		"SUBCMD2": 343,
		"MSGID": 94,
		"VOICEID": 10134,
		"NameJPN": "鴎",
		"JPN": "「危ない危ない。危うく誘導されるところだった」",
		"NameENG": "Kamome",
		"ENG": "\"Whew, that was close. You almost had me there for a second.\"",
		"Args": "0b"
	},
	{
		"LABEL": "0x181e",
		"Type": "MESSAGE",
		"SUBCMD": 3,
		"SUBCMD2": 345,
		"MSGID": 95,
		"NameJPN": "羽依里",
		"JPN": "「やっぱりぐろいんだな」",
		"NameENG": "Hairi",
		"ENG": "\"I knew it. It's gross, isn't it?\"",
		"Args": "0b"
	},
	{
		"LABEL": "0x1850",
		"Type": "IMAGEUPDATE",
		"SUBCMD": 1,
		"Args": "5b0101008e6c"
	},
	{
		"LABEL": "0x185a",
		"Type": "DRAW",
		"SUBCMD": 0,
		"Args": "0f00"
	},
	{
		"LABEL": "0x1860",
		"Type": "MESSAGE",
		"SUBCMD": 3,
		"SUBCMD2": 349,
		"MSGID": 96,
		"VOICEID": 10135,
		"NameJPN": "鴎",
		"JPN": "「ぐろくないっ」",
		"NameENG": "Kamome",
		"ENG": "\"It is not!\"",
		"Args": "0b"
	},
	{
		"LABEL": "0x1886",
		"Type": "GOTO",
		"SUBCMD": 1,
		"Args": "6101",
		"GOTO_LABEL": "0x2410"
	},
	{
		"LABEL": "0x1890",
		"Type": "CLOSE_WINDOW",
		"SUBCMD": 1,
		"Args": "6901"
	},
	{
		"LABEL": "0x1896",
		"Type": "IMAGELOAD",
		"SUBCMD": 0,
		"Args": "00006004000000000000"
	},
	{
		"LABEL": "0x18a4",
		"Type": "EQUN",
		"SUBCMD": 0,
		"Args": "3b1a0000"
	},
	{
		"LABEL": "0x18ac",
		"Type": "DRAW",
		"SUBCMD": 0,
		"Args": "1e00"
	},
	{
		"LABEL": "0x18b2",
		"Type": "WAIT",
		"SUBCMD": 0,
		"Args": ""
	},
	{
		"LABEL": "0x18b6",
		"Type": "MESSAGE",
		"SUBCMD": 3,
		"SUBCMD2": 363,
		"MSGID": 97,
		"VOICEID": 10136,
		"NameJPN": "鴎",
		"JPN": "「……着替えって」",
		"NameENG": "Kamome",
		"ENG": "\"Change...?\"",
		"Args": "0b"
	},
	{
		"LABEL": "0x18de",
		"Type": "MESSAGE",
		"SUBCMD": 3,
		"SUBCMD2": 365,
		"MSGID": 98,
		"VOICEID": 10137,
		"NameJPN": "鴎",
		"JPN": "「羽依里は、靴下１人で履けないタイプかな」",
		"NameENG": "Kamome",
		"ENG": "\"Are you the kinda guy who needs help putting his socks on?\"",
		"Args": "0b"
	},
	{
		"LABEL": "0x191e",
		"Type": "MESSAGE",
		"SUBCMD": 3,
		"SUBCMD2": 367,
		"MSGID": 99,
		"VOICEID": 10138,
		"NameJPN": "鴎",
		"JPN": "「子供によくいる」",
		"NameENG": "Kamome",
		"ENG": "\"There are a lot of kids like that.\"",
		"Args": "0b"
	},
	{
		"LABEL": "0x1946",
		"Type": "MESSAGE",
		"SUBCMD": 3,
		"SUBCMD2": 369,
		"MSGID": 100,
		"NameJPN": "羽依里",
		"JPN": "「……まぁ」",
		"NameENG": "Hairi",
		"ENG": "\"I mean...\"",
		"Args": "0b"
	},
	{
		"LABEL": "0x196c",
		"Type": "MESSAGE",
		"SUBCMD": 3,
		"SUBCMD2": 371,
		"MSGID": 101,
		"NameJPN": "羽依里",
		"JPN": "「今は若干、苦労するかな」",
		"NameENG": "Hairi",
		"ENG": "\"Given my current state, I could use a hand. Preferably one not in a cast.\"",
		"Args": "0b"
	},
	{
		"LABEL": "0x19a0",
		"Type": "MESSAGE",
		"SUBCMD": 3,
		"SUBCMD2": 373,
		"MSGID": 102,
		"VOICEID": 10139,
		"NameJPN": "鴎",
		"JPN": "「しょうがないな」",
		"NameENG": "Kamome",
		"ENG": "\"Oh, all right.\"",
		"Args": "0b"
	},
	{
		"LABEL": "0x19c8",
		"Type": "CLOSE_WINDOW",
		"SUBCMD": 1,
		"Args": "7701"
	},
	{
		"LABEL": "0x19ce",
		"Type": "IMAGELOAD",
		"SUBCMD": 0,
		"Args": "00005c04000000000000"
	},
	{
		"LABEL": "0x19dc",
		"Type": "EQUN",
		"SUBCMD": 0,
		"Args": "3b1a0000"
	},
	{
		"LABEL": "0x19e4",
		"Type": "DRAW",
		"SUBCMD": 0,
		"Args": "1e00"
	},
	{
		"LABEL": "0x19ea",
		"Type": "WAIT",
		"SUBCMD": 0,
		"Args": ""
	},
	{
		"LABEL": "0x19ee",
		"Type": "MESSAGE",
		"SUBCMD": 3,
		"SUBCMD2": 377,
		"MSGID": 103,
		"VOICEID": 10140,
		"NameJPN": "鴎",
		"JPN": "「じゃあ」",
		"NameENG": "Kamome",
		"ENG": "\"Now...\"",
		"Args": "0b"
	},
	{
		"LABEL": "0x1a0e",
		"Type": "MESSAGE",
		"SUBCMD": 3,
		"SUBCMD2": 379,
		"MSGID": 104,
		"VOICEID": 10141,
		"NameJPN": "鴎",
		"JPN": "「ちゃんと洗ってる靴下を２つ用意してください」",
		"NameENG": "Kamome",
		"ENG": "\"I'll need two well-washed socks, if ya please.\"",
		"Args": "0b"
	},
	{
		"LABEL": "0x1a52",
		"Type": "MESSAGE",
		"SUBCMD": 3,
		"SUBCMD2": 381,
		"MSGID": 105,
		"NameJPN": "羽依里",
		"JPN": "「どうぞ」",
		"NameENG": "Hairi",
		"ENG": "\"Here.\"",
		"Args": "0b"
	},
	{
		"LABEL": "0x1a76",
		"Type": "MESSAGE",
		"SUBCMD": 3,
		"SUBCMD2": 383,
		"MSGID": 106,
		"VOICEID": 10142,
		"NameJPN": "鴎",
		"JPN": "「ちゃんと洗った足を２つ差し出して下さい」",
		"NameENG": "Kamome",
		"ENG": "\"Two well-washed feet, if ya please.\"",
		"Args": "0b"
	},
	{
		"LABEL": "0x1ab6",
		"Type": "MESSAGE",
		"SUBCMD": 3,
		"SUBCMD2": 385,
		"MSGID": 107,
		"NameJPN": "羽依里",
		"JPN": "「ほい」",
		"NameENG": "Hairi",
		"ENG": "\"Hup.\"",
		"Args": "0b"
	},
	{
		"LABEL": "0x1ad8",
		"Type": "CLOSE_WINDOW",
		"SUBCMD": 1,
		"Args": "8301"
	},
	{
		"LABEL": "0x1ade",
		"Type": "IMAGELOAD",
		"SUBCMD": 0,
		"Args": "00005d04000000000000"
	},
	{
		"LABEL": "0x1aec",
		"Type": "EQUN",
		"SUBCMD": 0,
		"Args": "3b1a0000"
	},
	{
		"LABEL": "0x1af4",
		"Type": "DRAW",
		"SUBCMD": 0,
		"Args": "1e00"
	},
	{
		"LABEL": "0x1afa",
		"Type": "WAIT",
		"SUBCMD": 0,
		"Args": ""
	},
	{
		"LABEL": "0x1afe",
		"Type": "MESSAGE",
		"SUBCMD": 3,
		"SUBCMD2": 389,
		"MSGID": 108,
		"VOICEID": 10143,
		"NameJPN": "鴎",
		"JPN": "「……」",
		"NameENG": "Kamome",
		"ENG": "\"......\"",
		"Args": "0b"
	},
	{
		"LABEL": "0x1b1c",
		"Type": "MESSAGE",
		"SUBCMD": 3,
		"SUBCMD2": 391,
		"MSGID": 109,
		"VOICEID": 10144,
		"NameJPN": "鴎",
		"JPN": "「ちゃんと洗ってるんだね？」",
		"NameENG": "Kamome",
		"ENG": "\"These ARE well-washed, right?\"",
		"Args": "0b"
	},
	{
		"LABEL": "0x1b4e",
		"Type": "MESSAGE",
		"SUBCMD": 3,
		"SUBCMD2": 393,
		"MSGID": 110,
		"NameJPN": "羽依里",
		"JPN": "「洗ってるよ」",
		"NameENG": "Hairi",
		"ENG": "\"They are.\"",
		"Args": "0b"
	},
	{
		"LABEL": "0x1b76",
		"Type": "CLOSE_WINDOW",
		"SUBCMD": 1,
		"Args": "8b01"
	},
	{
		"LABEL": "0x1b7c",
		"Type": "IMAGELOAD",
		"SUBCMD": 0,
		"Args": "00003d00000000000000"
	},
	{
		"LABEL": "0x1b8a",
		"Type": "EQUN",
		"SUBCMD": 0,
		"Args": "3b1a0000"
	},
	{
		"LABEL": "0x1b92",
		"Type": "DRAW",
		"SUBCMD": 0,
		"Args": "3c00"
	},
	{
		"LABEL": "0x1b98",
		"Type": "WAIT",
		"SUBCMD": 0,
		"Args": ""
	},
	{
		"LABEL": "0x1b9c",
		"Type": "IMAGELOAD",
		"SUBCMD": 1,
		"Args": "8d010100886c00008002b400dd00"
	},
	{
		"LABEL": "0x1bae",
		"Type": "DRAW",
		"SUBCMD": 0,
		"Args": "0f00"
	},
	{
		"LABEL": "0x1bb4",
		"Type": "MESSAGE",
		"SUBCMD": 3,
		"SUBCMD2": 399,
		"MSGID": 111,
		"VOICEID": 10145,
		"NameJPN": "鴎",
		"JPN": "「では、失礼します」",
		"NameENG": "Kamome",
		"ENG": "\"Good, now if you'll excuse me.\"",
		"Args": "0b"
	},
	{
		"LABEL": "0x1bde",
		"Type": "MESSAGE",
		"SUBCMD": 3,
		"SUBCMD2": 401,
		"MSGID": 112,
		"NameJPN": "羽依里",
		"JPN": "「……」",
		"NameENG": "Hairi",
		"ENG": "\"......\"",
		"Args": "0b"
	},
	{
		"LABEL": "0x1c00",
		"Type": "IMAGEUPDATE",
		"SUBCMD": 1,
		"Args": "93010100866c"
	},
	{
		"LABEL": "0x1c0a",
		"Type": "DRAW",
		"SUBCMD": 0,
		"Args": "0f00"
	},
	{
		"LABEL": "0x1c10",
		"Type": "MESSAGE",
		"SUBCMD": 3,
		"SUBCMD2": 405,
		"MSGID": 113,
		"VOICEID": 10146,
		"NameJPN": "鴎",
		"JPN": "「……」",
		"NameENG": "Kamome",
		"ENG": "\"......\"",
		"Args": "0b"
	},
	{
		"LABEL": "0x1c2e",
		"Type": "IMAGEUPDATE",
		"SUBCMD": 1,
		"Args": "97010100726c"
	},
	{
		"LABEL": "0x1c38",
		"Type": "DRAW",
		"SUBCMD": 0,
		"Args": "0f00"
	},
	{
		"LABEL": "0x1c3e",
		"Type": "MESSAGE",
		"SUBCMD": 3,
		"SUBCMD2": 409,
		"MSGID": 114,
		"VOICEID": 10147,
		"NameJPN": "鴎",
		"JPN": "「ちゃんと洗ってる？」",
		"NameENG": "Kamome",
		"ENG": "\"How well-washed we talking?\"",
		"Args": "0b"
	},
	{
		"LABEL": "0x1c6a",
		"Type": "MESSAGE",
		"SUBCMD": 3,
		"SUBCMD2": 411,
		"MSGID": 115,
		"NameJPN": "羽依里",
		"JPN": "「洗ってるよ」",
		"NameENG": "Hairi",
		"ENG": "\"Very.\"",
		"Args": "0b"
	},
	{
		"LABEL": "0x1c92",
		"Type": "IMAGEUPDATE",
		"SUBCMD": 1,
		"Args": "9d010100866c"
	},
	{
		"LABEL": "0x1c9c",
		"Type": "DRAW",
		"SUBCMD": 0,
		"Args": "0f00"
	},
	{
		"LABEL": "0x1ca2",
		"Type": "MESSAGE",
		"SUBCMD": 3,
		"SUBCMD2": 415,
		"MSGID": 116,
		"VOICEID": 10148,
		"NameJPN": "鴎",
		"JPN": "「よいしょ」",
		"NameENG": "Kamome",
		"ENG": "\"There we go...\"",
		"Args": "0b"
	},
	{
		"LABEL": "0x1cc4",
		"Type": "QUAKE",
		"SUBCMD": 1,
		"Args": "a101ff0001060000520001010052"
	},
	{
		"LABEL": "0x1cd6",
		"Type": "QUAKE",
		"SUBCMD": 0,
		"Args": "ff0901060000520001010000"
	},
	{
		"LABEL": "0x1ce6",
		"Type": "MESSAGE",
		"SUBCMD": 3,
		"SUBCMD2": 419,
		"MSGID": 117,
		"NameJPN": "羽依里",
		"JPN": "「……っ」",
		"NameENG": "Hairi",
		"ENG": "\"...!\"",
		"Args": "0b"
	},
	{
		"LABEL": "0x1d0a",
		"Type": "IMAGEUPDATE",
		"SUBCMD": 1,
		"Args": "a5010100726c"
	},
	{
		"LABEL": "0x1d14",
		"Type": "DRAW",
		"SUBCMD": 0,
		"Args": "0f00"
	},
	{
		"LABEL": "0x1d1a",
		"Type": "MESSAGE",
		"SUBCMD": 3,
		"SUBCMD2": 423,
		"MSGID": 118,
		"VOICEID": 10149,
		"NameJPN": "鴎",
		"JPN": "「じっとしてよ」",
		"NameENG": "Kamome",
		"ENG": "\"Stay still, would you?\"",
		"Args": "0b"
	},
	{
		"LABEL": "0x1d40",
		"Type": "MESSAGE",
		"SUBCMD": 3,
		"SUBCMD2": 425,
		"MSGID": 119,
		"NameJPN": "羽依里",
		"JPN": "「なんかくすぐったいから」",
		"NameENG": "Hairi",
		"ENG": "\"It kinda tickles.\"",
		"Args": "0b"
	},
	{
		"LABEL": "0x1d74",
		"Type": "IMAGEUPDATE",
		"SUBCMD": 1,
		"Args": "ab010100826c"
	},
	{
		"LABEL": "0x1d7e",
		"Type": "DRAW",
		"SUBCMD": 0,
		"Args": "0f00"
	},
	{
		"LABEL": "0x1d84",
		"Type": "MESSAGE",
		"SUBCMD": 3,
		"SUBCMD2": 429,
		"MSGID": 120,
		"VOICEID": 10150,
		"NameJPN": "鴎",
		"JPN": "「なんで靴下履くだけでくすぐったいの」",
		"NameENG": "Kamome",
		"ENG": "\"Why would putting on socks tickle?\"",
		"Args": "0b"
	},
	{
		"LABEL": "0x1dc0",
		"Type": "MESSAGE",
		"SUBCMD": 3,
		"SUBCMD2": 431,
		"MSGID": 121,
		"NameJPN": "羽依里",
		"JPN": "「やられたら分かるよ」",
		"NameENG": "Hairi",
		"ENG": "\"You'd see what I mean if you tried it yourself.\"",
		"Args": "0b"
	},
	{
		"LABEL": "0x1df0",
		"Type": "IMAGEUPDATE",
		"SUBCMD": 1,
		"Args": "b1010100866c"
	},
	{
		"LABEL": "0x1dfa",
		"Type": "DRAW",
		"SUBCMD": 0,
		"Args": "0f00"
	},
	{
		"LABEL": "0x1e00",
		"Type": "MESSAGE",
		"SUBCMD": 3,
		"SUBCMD2": 435,
		"MSGID": 122,
		"VOICEID": 10151,
		"NameJPN": "鴎",
		"JPN": "「ほんとかな」",
		"NameENG": "Kamome",
		"ENG": "\"Would I?\"",
		"Args": "0b"
	},
	{
		"LABEL": "0x1e24",
		"Type": "IMAGEUPDATE",
		"SUBCMD": 1,
		"Args": "b5010100886c"
	},
	{
		"LABEL": "0x1e2e",
		"Type": "DRAW",
		"SUBCMD": 0,
		"Args": "0f00"
	},
	{
		"LABEL": "0x1e34",
		"Type": "MESSAGE",
		"SUBCMD": 3,
		"SUBCMD2": 439,
		"MSGID": 123,
		"VOICEID": 10152,
		"NameJPN": "鴎",
		"JPN": "「じゃあ私にも履かせてみてよ」",
		"NameENG": "Kamome",
		"ENG": "\"Okay, I'll bite. Try me.\"",
		"Args": "0b"
	},
	{
		"LABEL": "0x1e68",
		"Type": "MESSAGE",
		"SUBCMD": 3,
		"SUBCMD2": 441,
		"MSGID": 124,
		"NameJPN": "羽依里",
		"JPN": "「え」",
		"NameENG": "Hairi",
		"ENG": "\"Uh.\"",
		"Args": "0b"
	},
	{
		"LABEL": "0x1e88",
		"Type": "IMAGEUPDATE",
		"SUBCMD": 1,
		"Args": "bb0101007c6c"
	},
	{
		"LABEL": "0x1e92",
		"Type": "DRAW",
		"SUBCMD": 0,
		"Args": "0f00"
	},
	{
		"LABEL": "0x1e98",
		"Type": "MESSAGE",
		"SUBCMD": 3,
		"SUBCMD2": 445,
		"MSGID": 125,
		"VOICEID": 10153,
		"NameJPN": "鴎",
		"JPN": "「……は。そ、それが狙いか」",
		"NameENG": "Kamome",
		"ENG": "\"Hah! Th-This is exactly what you wanted, isn't it!?\"",
		"Args": "0b"
	},
	{
		"LABEL": "0x1eca",
		"Type": "MESSAGE",
		"SUBCMD": 3,
		"SUBCMD2": 447,
		"MSGID": 126,
		"NameJPN": "羽依里",
		"JPN": "「狙わない」",
		"NameENG": "Hairi",
		"ENG": "\"It is not.\"",
		"Args": "0b"
	},
	{
		"LABEL": "0x1ef0",
		"Type": "MESSAGE",
		"SUBCMD": 3,
		"SUBCMD2": 449,
		"MSGID": 127,
		"NameJPN": "羽依里",
		"JPN": "「俺は手を怪我してるから無理だし」",
		"NameENG": "Hairi",
		"ENG": "\"My arm's hurt. Which isn't conducive to putting on socks.\"",
		"Args": "0b"
	},
	{
		"LABEL": "0x1f2c",
		"Type": "MESSAGE",
		"SUBCMD": 3,
		"SUBCMD2": 451,
		"MSGID": 128,
		"NameJPN": "羽依里",
		"JPN": "「うみちゃん、履かせてあげて」",
		"NameENG": "Hairi",
		"ENG": "\"Umi-chan, help her put some socks on.\"",
		"Args": "0b"
	},
	{
		"LABEL": "0x1f64",
		"Type": "IMAGELOAD",
		"SUBCMD": 1,
		"Args": "c5010101dead00008002b4009100"
	},
	{
		"LABEL": "0x1f76",
		"Type": "FADE",
		"SUBCMD": 0,
		"Args": "0100000f00"
	},
	{
		"LABEL": "0x1f80",
		"Type": "DRAW",
		"SUBCMD": 0,
		"Args": "0f00"
	},
	{
		"LABEL": "0x1f86",
		"Type": "MESSAGE",
		"SUBCMD": 3,
		"SUBCMD2": 455,
		"MSGID": 129,
		"VOICEID": 28257,
		"NameJPN": "うみ",
		"JPN": "「あいあいさー」",
		"NameENG": "Umi",
		"ENG": "\"Aye aye, sir!\"",
		"Args": "0b"
	},
	{
		"LABEL": "0x1fae",
		"Type": "IMAGEUPDATE",
		"SUBCMD": 1,
		"Args": "c9010101a4ad"
	},
	{
		"LABEL": "0x1fb8",
		"Type": "MOVE",
		"SUBCMD": 0,
		"Args": "01010218009001b400"
	},
	{
		"LABEL": "0x1fc6",
		"Type": "PRIORITY",
		"SUBCMD": 0,
		"Args": "0101f500"
	},
	{
		"LABEL": "0x1fce",
		"Type": "IMAGELOAD",
		"SUBCMD": 0,
		"Args": "01006a6c00007003b400dd00"
	},
	{
		"LABEL": "0x1fde",
		"Type": "DRAW",
		"SUBCMD": 0,
		"Args": "0f00"
	},
	{
		"LABEL": "0x1fe4",
		"Type": "MESSAGE",
		"SUBCMD": 3,
		"SUBCMD2": 459,
		"MSGID": 130,
		"VOICEID": 28258,
		"NameJPN": "うみ",
		"JPN": "「よいしょっと……」",
		"NameENG": "Umi",
		"ENG": "\"On we go!\"",
		"Args": "0b"
	},
	{
		"LABEL": "0x2010",
		"Type": "MESSAGE",
		"SUBCMD": 3,
		"SUBCMD2": 461,
		"MSGID": 131,
		"JPN": "……",
		"ENG": "......",
		"Args": "0b"
	},
	{
		"LABEL": "0x2024",
		"Type": "IMAGEUPDATE",
		"SUBCMD": 1,
		"Args": "cf0101007c6c"
	},
	{
		"LABEL": "0x202e",
		"Type": "CUSTOMMOVE",
		"SUBCMD": 0,
		"Args": "01001600"
	},
	{
		"LABEL": "0x2036",
		"Type": "DRAW",
		"SUBCMD": 0,
		"Args": "0f00"
	},
	{
		"LABEL": "0x203c",
		"Type": "MESSAGE",
		"SUBCMD": 3,
		"SUBCMD2": 465,
		"MSGID": 132,
		"VOICEID": 10157,
		"NameJPN": "鴎",
		"JPN": "「ひゃぁ」",
		"NameENG": "Kamome",
		"ENG": "\"Hyaaah!\"",
		"Args": "0b"
	},
	{
		"LABEL": "0x205c",
		"Type": "IMAGEUPDATE",
		"SUBCMD": 1,
		"Args": "d3010100846c"
	},
	{
		"LABEL": "0x2066",
		"Type": "DRAW",
		"SUBCMD": 0,
		"Args": "0f00"
	},
	{
		"LABEL": "0x206c",
		"Type": "MESSAGE",
		"SUBCMD": 3,
		"SUBCMD2": 469,
		"MSGID": 133,
		"VOICEID": 10158,
		"NameJPN": "鴎",
		"JPN": "「くすぐったい」",
		"NameENG": "Kamome",
		"ENG": "\"It tickles!\"",
		"Args": "0b"
	},
	{
		"LABEL": "0x2092",
		"Type": "IMAGEUPDATE",
		"SUBCMD": 1,
		"Args": "d701010112ac"
	},
	{
		"LABEL": "0x209c",
		"Type": "DRAW",
		"SUBCMD": 0,
		"Args": "0f00"
	},
	{
		"LABEL": "0x20a2",
		"Type": "MESSAGE",
		"SUBCMD": 3,
		"SUBCMD2": 473,
		"MSGID": 134,
		"VOICEID": 28259,
		"NameJPN": "うみ",
		"JPN": "「おー、くすぐったい？」",
		"NameENG": "Umi",
		"ENG": "\"Ohhhh, it tickles?\"",
		"Args": "0b"
	},
	{
		"LABEL": "0x20d2",
		"Type": "IMAGEUPDATE",
		"SUBCMD": 1,
		"Args": "db0101010cac"
	},
	{
		"LABEL": "0x20dc",
		"Type": "DRAW",
		"SUBCMD": 0,
		"Args": "0f00"
	},
	{
		"LABEL": "0x20e2",
		"Type": "MESSAGE",
		"SUBCMD": 3,
		"SUBCMD2": 477,
		"MSGID": 135,
		"VOICEID": 28260,
		"NameJPN": "うみ",
		"JPN": "「わたしもはかせてー」",
		"NameENG": "Umi",
		"ENG": "\"Do me next!\"",
		"Args": "0b"
	},
	{
		"LABEL": "0x2110",
		"Type": "IMAGEUPDATE",
		"SUBCMD": 1,
		"Args": "df0101006a6c"
	},
	{
		"LABEL": "0x211a",
		"Type": "DRAW",
		"SUBCMD": 0,
		"Args": "0f00"
	},
	{
		"LABEL": "0x2120",
		"Type": "MESSAGE",
		"SUBCMD": 3,
		"SUBCMD2": 481,
		"MSGID": 136,
		"VOICEID": 10161,
		"NameJPN": "鴎",
		"JPN": "「うん」",
		"NameENG": "Kamome",
		"ENG": "\"Okay.\"",
		"Args": "0b"
	},
	{
		"LABEL": "0x213e",
		"Type": "MESSAGE",
		"SUBCMD": 3,
		"SUBCMD2": 483,
		"MSGID": 137,
		"JPN": "……",
		"ENG": "......",
		"Args": "0b"
	},
	{
		"LABEL": "0x2152",
		"Type": "IMAGEUPDATE",
		"SUBCMD": 1,
		"Args": "e5010101dcae"
	},
	{
		"LABEL": "0x215c",
		"Type": "CUSTOMMOVE",
		"SUBCMD": 0,
		"Args": "01011600"
	},
	{
		"LABEL": "0x2164",
		"Type": "DRAW",
		"SUBCMD": 0,
		"Args": "0f00"
	},
	{
		"LABEL": "0x216a",
		"Type": "MESSAGE",
		"SUBCMD": 3,
		"SUBCMD2": 487,
		"MSGID": 138,
		"VOICEID": 28261,
		"NameJPN": "うみ",
		"JPN": "「ひゃぁ、きゃきゃっ、くすぐったーい」",
		"NameENG": "Umi",
		"ENG": "\"Hyaaaau, ahaha! It tickles!\"",
		"Args": "0b"
	},
	{
		"LABEL": "0x21a8",
		"Type": "IMAGEUPDATE",
		"SUBCMD": 1,
		"Args": "e901010176ae"
	},
	{
		"LABEL": "0x21b2",
		"Type": "DRAW",
		"SUBCMD": 0,
		"Args": "0f00"
	},
	{
		"LABEL": "0x21b8",
		"Type": "MESSAGE",
		"SUBCMD": 3,
		"SUBCMD2": 491,
		"MSGID": 139,
		"VOICEID": 28262,
		"NameJPN": "うみ",
		"JPN": "「でも、なんかおもしろーい」",
		"NameENG": "Umi",
		"ENG": "\"But it's also kinda fun!\"",
		"Args": "0b"
	},
	{
		"LABEL": "0x21ec",
		"Type": "IMAGELOAD",
		"SUBCMD": 1,
		"Args": "ed010102c16f00008002b4008100"
	},
	{
		"LABEL": "0x21fe",
		"Type": "MOVE",
		"SUBCMD": 0,
		"Args": "01020000003e02b400"
	},
	{
		"LABEL": "0x220c",
		"Type": "MOVE",
		"SUBCMD": 0,
		"Args": "01020218008002b400"
	},
	{
		"LABEL": "0x221a",
		"Type": "FADE",
		"SUBCMD": 0,
		"Args": "0100000f00"
	},
	{
		"LABEL": "0x2224",
		"Type": "FADE",
		"SUBCMD": 0,
		"Args": "0101000f00"
	},
	{
		"LABEL": "0x222e",
		"Type": "DRAW",
		"SUBCMD": 0,
		"Args": "0f00"
	},
	{
		"LABEL": "0x2234",
		"Type": "MESSAGE",
		"SUBCMD": 3,
		"SUBCMD2": 495,
		"MSGID": 140,
		"VOICEID": 10165,
		"NameJPN": "鏡子",
		"JPN": "「……」",
		"NameENG": "Kyouko",
		"ENG": "\"......\"",
		"Args": "0b"
	},
	{
		"LABEL": "0x2254",
		"Type": "IMAGEUPDATE",
		"SUBCMD": 1,
		"Args": "f1010102df6f"
	},
	{
		"LABEL": "0x225e",
		"Type": "FADE",
		"SUBCMD": 0,
		"Args": "0100000f00"
	},
	{
		"LABEL": "0x2268",
		"Type": "FADE",
		"SUBCMD": 0,
		"Args": "0101000f00"
	},
	{
		"LABEL": "0x2272",
		"Type": "DRAW",
		"SUBCMD": 0,
		"Args": "0f00"
	},
	{
		"LABEL": "0x2278",
		"Type": "MESSAGE",
		"SUBCMD": 3,
		"SUBCMD2": 499,
		"MSGID": 141,
		"VOICEID": 10166,
		"NameJPN": "鏡子",
		"JPN": "「何してるのかな」",
		"NameENG": "Kyouko",
		"ENG": "\"What are you all doing?\"",
		"Args": "0b"
	},
	{
		"LABEL": "0x22a2",
		"Type": "MESSAGE",
		"SUBCMD": 3,
		"SUBCMD2": 501,
		"MSGID": 142,
		"NameJPN": "羽依里",
		"JPN": "「人に靴下を履かせてもらうと妙にくすぐったい説の調査です」",
		"NameENG": "Hairi",
		"ENG": "\"An experiment. Hypothesis: Having someone else put socks on you tickles.\"",
		"Args": "0b"
	},
	{
		"LABEL": "0x22f6",
		"Type": "IMAGEUPDATE",
		"SUBCMD": 1,
		"Args": "f7010102016f"
	},
	{
		"LABEL": "0x2300",
		"Type": "FADE",
		"SUBCMD": 0,
		"Args": "0100000f00"
	},
	{
		"LABEL": "0x230a",
		"Type": "FADE",
		"SUBCMD": 0,
		"Args": "0101000f00"
	},
	{
		"LABEL": "0x2314",
		"Type": "DRAW",
		"SUBCMD": 0,
		"Args": "0f00"
	},
	{
		"LABEL": "0x231a",
		"Type": "MESSAGE",
		"SUBCMD": 3,
		"SUBCMD2": 505,
		"MSGID": 143,
		"VOICEID": 10167,
		"NameJPN": "鏡子",
		"JPN": "「えええ」",
		"NameENG": "Kyouko",
		"ENG": "\"What?\"",
		"Args": "0b"
	},
	{
		"LABEL": "0x233c",
		"Type": "IMAGEUPDATE",
		"SUBCMD": 1,
		"Args": "fb010102d36e"
	},
	{
		"LABEL": "0x2346",
		"Type": "CUSTOMMOVE",
		"SUBCMD": 0,
		"Args": "01020100"
	},
	{
		"LABEL": "0x234e",
		"Type": "FADE",
		"SUBCMD": 0,
		"Args": "0100000f00"
	},
	{
		"LABEL": "0x2358",
		"Type": "FADE",
		"SUBCMD": 0,
		"Args": "0101000f00"
	},
	{
		"LABEL": "0x2362",
		"Type": "DRAW",
		"SUBCMD": 0,
		"Args": "0f00"
	},
	{
		"LABEL": "0x2368",
		"Type": "MESSAGE",
		"SUBCMD": 3,
		"SUBCMD2": 509,
		"MSGID": 144,
		"VOICEID": 10168,
		"NameJPN": "鏡子",
		"JPN": "「私も、ちょっとお願い」",
		"NameENG": "Kyouko",
		"ENG": "\"Let me give it a try!\"",
		"Args": "0b"
	},
	{
		"LABEL": "0x2398",
		"Type": "CLOSE_WINDOW",
		"SUBCMD": 1,
		"Args": "0002"
	},
	{
		"LABEL": "0x239e",
		"Type": "INIT",
		"SUBCMD": 0,
		"Args": "0100"
	},
	{
		"LABEL": "0x23a4",
		"Type": "INIT",
		"SUBCMD": 0,
		"Args": "0101"
	},
	{
		"LABEL": "0x23aa",
		"Type": "INIT",
		"SUBCMD": 0,
		"Args": "0102"
	},
	{
		"LABEL": "0x23b0",
		"Type": "IMAGELOAD",
		"SUBCMD": 0,
		"Args": "00009e00000000000000"
	},
	{
		"LABEL": "0x23be",
		"Type": "EQUN",
		"SUBCMD": 0,
		"Args": "3b1a0000"
	},
	{
		"LABEL": "0x23c6",
		"Type": "DRAW",
		"SUBCMD": 0,
		"Args": "3c00"
	},
	{
		"LABEL": "0x23cc",
		"Type": "WAIT",
		"SUBCMD": 0,
		"Args": ""
	},
	{
		"LABEL": "0x23d0",
		"Type": "IMAGELOAD",
		"SUBCMD": 1,
		"Args": "02020600296f0900790075ff"
	},
	{
		"LABEL": "0x23e0",
		"Type": "MESSAGE",
		"SUBCMD": 3,
		"SUBCMD2": 517,
		"MSGID": 145,
		"VOICEID": 10169,
		"NameJPN": "鏡子",
		"JPN": "「ひゃぁ、くすぐったい」",
		"NameENG": "Kyouko",
		"ENG": "\"Hyaaah, that tickles!\"",
		"Args": "0b"
	},
	{
		"LABEL": "0x2410",
		"Type": "CLOSE_WINDOW",
		"SUBCMD": 1,
		"Args": "0d02"
	},
	{
		"LABEL": "0x2416",
		"Type": "EQUN",
		"SUBCMD": 0,
		"Args": "3b1a0000"
	},
	{
		"LABEL": "0x241e",
		"Type": "INIT",
		"SUBCMD": 0,
		"Args": "0100"
	},
	{
		"LABEL": "0x2424",
		"Type": "IMAGELOAD",
		"SUBCMD": 0,
		"Args": "0000b800000000000000"
	},
	{
		"LABEL": "0x2432",
		"Type": "INIT",
		"SUBCMD": 0,
		"Args": "01ff"
	},
	{
		"LABEL": "0x2438",
		"Type": "DRAW",
		"SUBCMD": 0,
		"Args": "3c00"
	},
	{
		"LABEL": "0x243e",
		"Type": "WAIT",
		"SUBCMD": 0,
		"Args": ""
	},
	{
		"LABEL": "0x2442",
		"Type": "WAIT",
		"SUBCMD": 0,
		"Args": "3c00"
	},
	{
		"LABEL": "0x2448",
		"Type": "CLOSE_WINDOW",
		"SUBCMD": 1,
		"Args": "1302"
	},
	{
		"LABEL": "0x244e",
		"Type": "IMAGELOAD",
		"SUBCMD": 0,
		"Args": "00005c04000000000000"
	},
	{
		"LABEL": "0x245c",
		"Type": "EQUN",
		"SUBCMD": 0,
		"Args": "3b1a0000"
	},
	{
		"LABEL": "0x2464",
		"Type": "DRAW",
		"SUBCMD": 0,
		"Args": "3c00"
	},
	{
		"LABEL": "0x246a",
		"Type": "WAIT",
		"SUBCMD": 0,
		"Args": ""
	},
	{
		"LABEL": "0x246e",
		"Type": "MESSAGE",
		"SUBCMD": 3,
		"SUBCMD2": 533,
		"MSGID": 146,
		"NameJPN": "羽依里",
		"JPN": "「次は風呂を手伝ってくれ」",
		"NameENG": "Hairi",
		"ENG": "\"Can you help me with the bath next?\"",
		"Args": "0b"
	},
	{
		"LABEL": "0x24a2",
		"Type": "MESSAGE",
		"SUBCMD": 3,
		"SUBCMD2": 535,
		"MSGID": 147,
		"JPN": "風呂を掃除してわかすのは俺の役目だけど、手を怪我して困っていたんだ。",
		"ENG": "Cleaning and preparing the bath was supposed to be one of my chores, but my arm put a damper on that.",
		"Args": "0b"
	},
	{
		"LABEL": "0x24f6",
		"Type": "CLOSE_WINDOW",
		"SUBCMD": 1,
		"Args": "1902"
	},
	{
		"LABEL": "0x24fc",
		"Type": "IMAGELOAD",
		"SUBCMD": 0,
		"Args": "00005f04000000000000"
	},
	{
		"LABEL": "0x250a",
		"Type": "EQUN",
		"SUBCMD": 0,
		"Args": "3b1a0000"
	},
	{
		"LABEL": "0x2512",
		"Type": "DRAW",
		"SUBCMD": 0,
		"Args": "1e00"
	},
	{
		"LABEL": "0x2518",
		"Type": "WAIT",
		"SUBCMD": 0,
		"Args": ""
	},
	{
		"LABEL": "0x251c",
		"Type": "MESSAGE",
		"SUBCMD": 3,
		"SUBCMD2": 539,
		"MSGID": 148,
		"VOICEID": 10170,
		"NameJPN": "鴎",
		"JPN": "「え」",
		"NameENG": "Kamome",
		"ENG": "\"Wha...\"",
		"Args": "0b"
	},
	{
		"LABEL": "0x2538",
		"Type": "MESSAGE",
		"SUBCMD": 3,
		"SUBCMD2": 541,
		"MSGID": 149,
		"VOICEID": 10171,
		"NameJPN": "鴎",
		"JPN": "「マジで」",
		"NameENG": "Kamome",
		"ENG": "\"Like, for reals?\"",
		"Args": "0b"
	},
	{
		"LABEL": "0x2558",
		"Type": "MESSAGE",
		"SUBCMD": 3,
		"SUBCMD2": 543,
		"MSGID": 150,
		"NameJPN": "羽依里",
		"JPN": "「マジだ」",
		"NameENG": "Hairi",
		"ENG": "\"For super reals.\"",
		"Args": "0b"
	},
	{
		"LABEL": "0x257c",
		"Type": "CLOSE_WINDOW",
		"SUBCMD": 1,
		"Args": "2102"
	},
	{
		"LABEL": "0x2582",
		"Type": "IMAGELOAD",
		"SUBCMD": 0,
		"Args": "00005d04000000000000"
	},
	{
		"LABEL": "0x2590",
		"Type": "EQUN",
		"SUBCMD": 0,
		"Args": "3b1a0000"
	},
	{
		"LABEL": "0x2598",
		"Type": "DRAW",
		"SUBCMD": 0,
		"Args": "1e00"
	},
	{
		"LABEL": "0x259e",
		"Type": "WAIT",
		"SUBCMD": 0,
		"Args": ""
	},
	{
		"LABEL": "0x25a2",
		"Type": "MESSAGE",
		"SUBCMD": 3,
		"SUBCMD2": 547,
		"MSGID": 151,
		"VOICEID": 10172,
		"NameJPN": "鴎",
		"JPN": "「わ、分かった」",
		"NameENG": "Kamome",
		"ENG": "\"O... Okay.\"",
		"Args": "0b"
	},
	{
		"LABEL": "0x25c8",
		"Type": "MESSAGE",
		"SUBCMD": 3,
		"SUBCMD2": 549,
		"MSGID": 152,
		"VOICEID": 10173,
		"NameJPN": "鴎",
		"JPN": "「鴎に二言はない」",
		"NameENG": "Kamome",
		"ENG": "\"Gulls never go back on their word.\"",
		"Args": "0b"
	},
	{
		"LABEL": "0x25f0",
		"Type": "MESSAGE",
		"SUBCMD": 3,
		"SUBCMD2": 551,
		"MSGID": 153,
		"VOICEID": 10174,
		"NameJPN": "鴎",
		"JPN": "「手伝うよ」",
		"NameENG": "Kamome",
		"ENG": "\"I'll help you out.\"",
		"Args": "0b"
	},
	{
		"LABEL": "0x2612",
		"Type": "MESSAGE",
		"SUBCMD": 3,
		"SUBCMD2": 553,
		"MSGID": 154,
		"NameJPN": "羽依里",
		"JPN": "「あぁ、よろしくな」",
		"NameENG": "Hairi",
		"ENG": "\"Thanks.\"",
		"Args": "0b"
	},
	{
		"LABEL": "0x2640",
		"Type": "BGM",
		"SUBCMD": 1,
		"Args": "2b02000000007800"
	},
	{
		"LABEL": "0x264c",
		"Type": "CLOSE_WINDOW",
		"SUBCMD": 1,
		"Args": "2e02"
	},
	{
		"LABEL": "0x2652",
		"Type": "EQUN",
		"SUBCMD": 0,
		"Args": "3b1a0000"
	},
	{
		"LABEL": "0x265a",
		"Type": "IMAGELOAD",
		"SUBCMD": 0,
		"Args": "0000b800000000000000"
	},
	{
		"LABEL": "0x2668",
		"Type": "INIT",
		"SUBCMD": 0,
		"Args": "01ff"
	},
	{
		"LABEL": "0x266e",
		"Type": "DRAW",
		"SUBCMD": 0,
		"Args": "3c00"
	},
	{
		"LABEL": "0x2674",
		"Type": "WAIT",
		"SUBCMD": 0,
		"Args": ""
	},
	{
		"LABEL": "0x2678",
		"Type": "WAIT",
		"SUBCMD": 0,
		"Args": "3c00"
	},
	{
		"LABEL": "0x267e",
		"Type": "EQUN",
		"SUBCMD": 1,
		"Args": "3002d11b0200"
	},
	{
		"LABEL": "0x2688",
		"Type": "BGM",
		"SUBCMD": 1,
		"Args": "3202b1860100"
	},
	{
		"LABEL": "0x2692",
		"Type": "CLOSE_WINDOW",
		"SUBCMD": 1,
		"Args": "3602"
	},
	{
		"LABEL": "0x2698",
		"Type": "IMAGELOAD",
		"SUBCMD": 0,
		"Args": "00004800000000000000"
	},
	{
		"LABEL": "0x26a6",
		"Type": "EQUN",
		"SUBCMD": 0,
		"Args": "3b1a0000"
	},
	{
		"LABEL": "0x26ae",
		"Type": "DRAW",
		"SUBCMD": 0,
		"Args": "3c00"
	},
	{
		"LABEL": "0x26b4",
		"Type": "WAIT",
		"SUBCMD": 0,
		"Args": ""
	},
	{
		"LABEL": "0x26b8",
		"Type": "IMAGELOAD",
		"SUBCMD": 1,
		"Args": "3802060076ad09006b00dcfe"
	},
	{
		"LABEL": "0x26c8",
		"Type": "MESSAGE",
		"SUBCMD": 3,
		"SUBCMD2": 570,
		"MSGID": 155,
		"VOICEID": 28263,
		"NameJPN": "うみ",
		"JPN": "「おにーちゃーん、おーふーろー」",
		"NameENG": "Umi",
		"ENG": "\"Onii-chan, bath time!\"",
		"Args": "0b"
	},
	{
		"LABEL": "0x2700",
		"Type": "MESSAGE",
		"SUBCMD": 3,
		"SUBCMD2": 572,
		"MSGID": 156,
		"NameJPN": "羽依里",
		"JPN": "「あぁ」",
		"NameENG": "Hairi",
		"ENG": "\"Okay.\"",
		"Args": "0b"
	},
	{
		"LABEL": "0x2722",
		"Type": "MESSAGE",
		"SUBCMD": 3,
		"SUBCMD2": 574,
		"MSGID": 157,
		"JPN": "晩ご飯を終えて部屋で横になっていると、うみちゃんから声がかかった。",
		"ENG": "Umi-chan called for me while I was relaxing in my room after dinner.",
		"Args": "0b"
	},
	{
		"LABEL": "0x2774",
		"Type": "MESSAGE",
		"SUBCMD": 3,
		"SUBCMD2": 576,
		"MSGID": 158,
		"JPN": "……そういえば、鴎はもう帰ったのかな。",
		"ENG": "I assume Kamome went home already.",
		"Args": "0b"
	},
	{
		"LABEL": "0x27aa",
		"Type": "MESSAGE",
		"SUBCMD": 3,
		"SUBCMD2": 578,
		"MSGID": 159,
		"JPN": "時間が時間だしな。",
		"ENG": "She couldn't just stick around forever, after all.",
		"Args": "0b"
	},
	{
		"LABEL": "0x27cc",
		"Type": "CLOSE_WINDOW",
		"SUBCMD": 1,
		"Args": "4402"
	},
	{
		"LABEL": "0x27d2",
		"Type": "EQUN",
		"SUBCMD": 0,
		"Args": "3b1a0000"
	},
	{
		"LABEL": "0x27da",
		"Type": "IMAGELOAD",
		"SUBCMD": 0,
		"Args": "0000b800000000000000"
	},
	{
		"LABEL": "0x27e8",
		"Type": "INIT",
		"SUBCMD": 0,
		"Args": "01ff"
	},
	{
		"LABEL": "0x27ee",
		"Type": "DRAW",
		"SUBCMD": 0,
		"Args": "3c00"
	},
	{
		"LABEL": "0x27f4",
		"Type": "WAIT",
		"SUBCMD": 0,
		"Args": ""
	},
	{
		"LABEL": "0x27f8",
		"Type": "WAIT",
		"SUBCMD": 0,
		"Args": "3c00"
	},
	{
		"LABEL": "0x27fe",
		"Type": "SE",
		"SUBCMD": 1,
		"Args": "460205950d0300"
	},
	{
		"LABEL": "0x280a",
		"Type": "WAIT",
		"SUBCMD": 1,
		"Args": "47025a00"
	},
	{
		"LABEL": "0x2812",
		"Type": "IMAGELOAD",
		"SUBCMD": 1,
		"Args": "4a020001fa01"
	},
	{
		"LABEL": "0x281c",
		"Type": "SCALE",
		"SUBCMD": 0,
		"Args": "0001000003406b40"
	},
	{
		"LABEL": "0x2828",
		"Type": "BMODE",
		"SUBCMD": 0,
		"Args": "000102"
	},
	{
		"LABEL": "0x2830",
		"Type": "FADE",
		"SUBCMD": 0,
		"Args": "0001c8"
	},
	{
		"LABEL": "0x2838",
		"Type": "MOVE",
		"SUBCMD": 0,
		"Args": "0001000000ffffb9ff"
	},
	{
		"LABEL": "0x2846",
		"Type": "IMAGELOAD",
		"SUBCMD": 0,
		"Args": "0309fa0103"
	},
	{
		"LABEL": "0x2850",
		"Type": "SCALE",
		"SUBCMD": 0,
		"Args": "0309000003406b40"
	},
	{
		"LABEL": "0x285c",
		"Type": "BMODE",
		"SUBCMD": 0,
		"Args": "000902"
	},
	{
		"LABEL": "0x2864",
		"Type": "FADE",
		"SUBCMD": 0,
		"Args": "0309c8"
	},
	{
		"LABEL": "0x286c",
		"Type": "MOVE",
		"SUBCMD": 0,
		"Args": "0309000000fafab9ff"
	},
	{
		"LABEL": "0x287a",
		"Type": "CLOSE_WINDOW",
		"SUBCMD": 1,
		"Args": "4b02"
	},
	{
		"LABEL": "0x2880",
		"Type": "IMAGELOAD",
		"SUBCMD": 0,
		"Args": "0000b300000000000000"
	},
	{
		"LABEL": "0x288e",
		"Type": "EQUN",
		"SUBCMD": 0,
		"Args": "3b1a0100"
	},
	{
		"LABEL": "0x2896",
		"Type": "DRAW",
		"SUBCMD": 0,
		"Args": "3c00"
	},
	{
		"LABEL": "0x289c",
		"Type": "WAIT",
		"SUBCMD": 0,
		"Args": ""
	},
	{
		"LABEL": "0x28a0",
		"Type": "MESSAGE",
		"SUBCMD": 3,
		"SUBCMD2": 590,
		"MSGID": 160,
		"NameJPN": "羽依里",
		"JPN": "「ふぅ……」",
		"NameENG": "Hairi",
		"ENG": "\"Whew...\"",
		"Args": "0b"
	},
	{
		"LABEL": "0x28c6",
		"Type": "MESSAGE",
		"SUBCMD": 3,
		"SUBCMD2": 592,
		"MSGID": 161,
		"JPN": "鴎は風呂掃除をしてくれたんだろうか。",
		"ENG": "Kamome probably cleaned the tub for me.",
		"Args": "0b"
	},
	{
		"LABEL": "0x28fa",
		"Type": "MESSAGE",
		"SUBCMD": 3,
		"SUBCMD2": 594,
		"MSGID": 162,
		"JPN": "よその女子が洗った風呂に入っている……",
		"ENG": "That same tub I'm currently sitting in...",
		"Args": "0b"
	},
	{
		"LABEL": "0x2930",
		"Type": "MESSAGE",
		"SUBCMD": 3,
		"SUBCMD2": 596,
		"MSGID": 163,
		"JPN": "それってなんか。",
		"ENG": "Almost like...",
		"Args": "0b"
	},
	{
		"LABEL": "0x2950",
		"Type": "MESSAGE",
		"SUBCMD": 3,
		"SUBCMD2": 598,
		"MSGID": 164,
		"NameJPN": "羽依里",
		"JPN": "「鷹原羽依里っ」",
		"NameENG": "Hairi",
		"ENG": "\"Takahara Hairi!\"",
		"Args": "0b"
	},
	{
		"LABEL": "0x297a",
		"Type": "MESSAGE",
		"SUBCMD": 3,
		"SUBCMD2": 600,
		"MSGID": 165,
		"JPN": "よその女子が洗った風呂に入るのがなんだと言うんだっ。",
		"ENG": "The nature of the basin in which you soak matters not!",
		"Args": "0b"
	},
	{
		"LABEL": "0x29be",
		"Type": "SE",
		"SUBCMD": 1,
		"Args": "5b02051e0e0300"
	},
	{
		"LABEL": "0x29ca",
		"Type": "BGM",
		"SUBCMD": 1,
		"Args": "5d02000000007800"
	},
	{
		"LABEL": "0x29d6",
		"Type": "INIT",
		"SUBCMD": 1,
		"Args": "5f020001"
	},
	{
		"LABEL": "0x29de",
		"Type": "BMODE",
		"SUBCMD": 0,
		"Args": "000100"
	},
	{
		"LABEL": "0x29e6",
		"Type": "MOVE",
		"SUBCMD": 0,
		"Args": "000100000000000000"
	},
	{
		"LABEL": "0x29f4",
		"Type": "SCALE",
		"SUBCMD": 0,
		"Args": "0001"
	},
	{
		"LABEL": "0x29fa",
		"Type": "INIT",
		"SUBCMD": 0,
		"Args": "0309"
	},
	{
		"LABEL": "0x2a00",
		"Type": "BMODE",
		"SUBCMD": 0,
		"Args": "030900"
	},
	{
		"LABEL": "0x2a08",
		"Type": "MOVE",
		"SUBCMD": 0,
		"Args": "030900000000000000"
	},
	{
		"LABEL": "0x2a16",
		"Type": "SCALE",
		"SUBCMD": 0,
		"Args": "0309"
	},
	{
		"LABEL": "0x2a1c",
		"Type": "CLOSE_WINDOW",
		"SUBCMD": 1,
		"Args": "6002"
	},
	{
		"LABEL": "0x2a22",
		"Type": "IMAGELOAD",
		"SUBCMD": 0,
		"Args": "0000bb00000000000000"
	},
	{
		"LABEL": "0x2a30",
		"Type": "EQUN",
		"SUBCMD": 0,
		"Args": "3b1a0000"
	},
	{
		"LABEL": "0x2a38",
		"Type": "DRAW",
		"SUBCMD": 0,
		"Args": "3c00"
	},
	{
		"LABEL": "0x2a3e",
		"Type": "WAIT",
		"SUBCMD": 0,
		"Args": ""
	},
	{
		"LABEL": "0x2a42",
		"Type": "MESSAGE",
		"SUBCMD": 3,
		"SUBCMD2": 610,
		"MSGID": 166,
		"JPN": "と、しばらく入っていると、不意にがららとドアが開いた。",
		"ENG": "A bit later and, suddenly, the door rattled open.",
		"Args": "0b"
	},
	{
		"LABEL": "0x2a88",
		"Type": "MESSAGE",
		"SUBCMD": 3,
		"SUBCMD2": 614,
		"MSGID": 167,
		"NameJPN": "羽依里",
		"JPN": "「え゛」",
		"NameENG": "Hairi",
		"ENG": "\"Bwuh!\"",
		"Args": "0b"
	},
	{
		"LABEL": "0x2aaa",
		"Type": "MESSAGE",
		"SUBCMD": 3,
		"SUBCMD2": 616,
		"MSGID": 168,
		"NameJPN": "羽依里",
		"JPN": "「誰」",
		"NameENG": "Hairi",
		"ENG": "\"Who's there!?\"",
		"Args": "0b"
	},
	{
		"LABEL": "0x2aca",
		"Type": "SE",
		"SUBCMD": 1,
		"Args": "6b0205"
	},
	{
		"LABEL": "0x2ad2",
		"Type": "BGM",
		"SUBCMD": 1,
		"Args": "6d02b2860100"
	},
	{
		"LABEL": "0x2adc",
		"Type": "IMAGELOAD",
		"SUBCMD": 1,
		"Args": "6f020600876c0900650061ff"
	},
	{
		"LABEL": "0x2aec",
		"Type": "MESSAGE",
		"SUBCMD": 3,
		"SUBCMD2": 625,
		"MSGID": 169,
		"VOICEID": 10176,
		"NameJPN": "鴎",
		"JPN": "「背中流すよ」",
		"NameENG": "Kamome",
		"ENG": "\"Me! Come to wash your back!\"",
		"Args": "0b"
	},
	{
		"LABEL": "0x2b10",
		"Type": "MESSAGE",
		"SUBCMD": 3,
		"SUBCMD2": 627,
		"MSGID": 170,
		"NameJPN": "羽依里",
		"JPN": "「どわ」",
		"NameENG": "Hairi",
		"ENG": "\"Whuaagh!?\"",
		"Args": "0b"
	},
	{
		"LABEL": "0x2b32",
		"Type": "MESSAGE",
		"SUBCMD": 3,
		"SUBCMD2": 629,
		"MSGID": 171,
		"JPN": "鴎だった。",
		"ENG": "It was Kamome.",
		"Args": "0b"
	},
	{
		"LABEL": "0x2b4c",
		"Type": "MESSAGE",
		"SUBCMD": 3,
		"SUBCMD2": 631,
		"MSGID": 172,
		"NameJPN": "羽依里",
		"JPN": "「なんでいる！」",
		"NameENG": "Hairi",
		"ENG": "\"Why are you here!?\"",
		"Args": "0b"
	},
	{
		"LABEL": "0x2b76",
		"Type": "IMAGELOAD",
		"SUBCMD": 1,
		"Args": "79020600736c0900650061ff"
	},
	{
		"LABEL": "0x2b86",
		"Type": "MESSAGE",
		"SUBCMD": 3,
		"SUBCMD2": 635,
		"MSGID": 173,
		"VOICEID": 10177,
		"NameJPN": "鴎",
		"JPN": "「なんでって、手伝いにきたんだよ」",
		"NameENG": "Kamome",
		"ENG": "\"Well that's a funny question. I'm here to help.\"",
		"Args": "0b"
	},
	{
		"LABEL": "0x2bbe",
		"Type": "MESSAGE",
		"SUBCMD": 3,
		"SUBCMD2": 637,
		"MSGID": 174,
		"NameJPN": "羽依里",
		"JPN": "「ええ」",
		"NameENG": "Hairi",
		"ENG": "\"I'm sorry?\"",
		"Args": "0b"
	},
	{
		"LABEL": "0x2be0",
		"Type": "MESSAGE",
		"SUBCMD": 3,
		"SUBCMD2": 639,
		"MSGID": 175,
		"NameJPN": "羽依里",
		"JPN": "「だ、だってお前」",
		"NameENG": "Hairi",
		"ENG": "\"B-But you―\"",
		"Args": "0b"
	},
	{
		"LABEL": "0x2c0c",
		"Type": "IMAGELOAD",
		"SUBCMD": 1,
		"Args": "810206006d6c0900650061ff"
	},
	{
		"LABEL": "0x2c1c",
		"Type": "MESSAGE",
		"SUBCMD": 3,
		"SUBCMD2": 643,
		"MSGID": 176,
		"VOICEID": 10178,
		"NameJPN": "鴎",
		"JPN": "「そんな恥ずかしがらなくても」",
		"NameENG": "Kamome",
		"ENG": "\"You don't gotta be so embarrassed.\"",
		"Args": "0b"
	},
	{
		"LABEL": "0x2c50",
		"Type": "IMAGELOAD",
		"SUBCMD": 1,
		"Args": "85020600696c0900650061ff"
	},
	{
		"LABEL": "0x2c60",
		"Type": "MESSAGE",
		"SUBCMD": 3,
		"SUBCMD2": 647,
		"MSGID": 177,
		"VOICEID": 10179,
		"NameJPN": "鴎",
		"JPN": "「タオルしてるんでしょう」",
		"NameENG": "Kamome",
		"ENG": "\"You have a towel on, don't you?\"",
		"Args": "0b"
	},
	{
		"LABEL": "0x2c90",
		"Type": "MESSAGE",
		"SUBCMD": 3,
		"SUBCMD2": 649,
		"MSGID": 178,
		"NameJPN": "羽依里",
		"JPN": "「してない」",
		"NameENG": "Hairi",
		"ENG": "\"No.\"",
		"Args": "0b"
	},
	{
		"LABEL": "0x2cb6",
		"Type": "IMAGELOAD",
		"SUBCMD": 1,
		"Args": "8b0206007b6c0900650061ff"
	},
	{
		"LABEL": "0x2cc6",
		"Type": "MESSAGE",
		"SUBCMD": 3,
		"SUBCMD2": 653,
		"MSGID": 179,
		"VOICEID": 10180,
		"NameJPN": "鴎",
		"JPN": "「えええ」",
		"NameENG": "Kamome",
		"ENG": "\"No!?\"",
		"Args": "0b"
	},
	{
		"LABEL": "0x2ce6",
		"Type": "IMAGELOAD",
		"SUBCMD": 1,
		"Args": "8f020600716c0900650061ff"
	},
	{
		"LABEL": "0x2cf6",
		"Type": "MESSAGE",
		"SUBCMD": 3,
		"SUBCMD2": 657,
		"MSGID": 180,
		"VOICEID": 10181,
		"NameJPN": "鴎",
		"JPN": "「人に手伝わせておいて、何してるの」",
		"NameENG": "Kamome",
		"ENG": "\"You're the one who asked for me! What's the matter with you!?\"",
		"Args": "0b"
	},
	{
		"LABEL": "0x2d30",
		"Type": "IMAGELOAD",
		"SUBCMD": 1,
		"Args": "93020600836c0900650061ff"
	},
	{
		"LABEL": "0x2d40",
		"Type": "MESSAGE",
		"SUBCMD": 3,
		"SUBCMD2": 661,
		"MSGID": 181,
		"VOICEID": 10182,
		"NameJPN": "鴎",
		"JPN": "「タオルぐらいしてよ」",
		"NameENG": "Kamome",
		"ENG": "\"Is a towel asking too much?\"",
		"Args": "0b"
	},
	{
		"LABEL": "0x2d6c",
		"Type": "MESSAGE",
		"SUBCMD": 3,
		"SUBCMD2": 663,
		"MSGID": 182,
		"NameJPN": "羽依里",
		"JPN": "「待て。手伝えってのは、掃除とかであって」",
		"NameENG": "Hairi",
		"ENG": "\"Wait. When I asked for you, I meant for help with cleaning.\"",
		"Args": "0b"
	},
	{
		"LABEL": "0x2db0",
		"Type": "MESSAGE",
		"SUBCMD": 3,
		"SUBCMD2": 665,
		"MSGID": 183,
		"NameJPN": "羽依里",
		"JPN": "「誰も背中を流してくれなんて言わないよ」",
		"NameENG": "Hairi",
		"ENG": "\"Not to wash my back. God no.\"",
		"Args": "0b"
	},
	{
		"LABEL": "0x2df2",
		"Type": "IMAGELOAD",
		"SUBCMD": 1,
		"Args": "9b020600856c0900650061ff"
	},
	{
		"LABEL": "0x2e02",
		"Type": "MESSAGE",
		"SUBCMD": 3,
		"SUBCMD2": 669,
		"MSGID": 184,
		"VOICEID": 10183,
		"NameJPN": "鴎",
		"JPN": "「でも、お風呂、最初から沸いてたよ？」",
		"NameENG": "Kamome",
		"ENG": "\"But the bath's been filled for a while now.\"",
		"Args": "0b"
	},
	{
		"LABEL": "0x2e3e",
		"Type": "MESSAGE",
		"SUBCMD": 3,
		"SUBCMD2": 671,
		"MSGID": 185,
		"NameJPN": "羽依里",
		"JPN": "「なに」",
		"NameENG": "Hairi",
		"ENG": "\"What?\"",
		"Args": "0b"
	},
	{
		"LABEL": "0x2e60",
		"Type": "IMAGELOAD",
		"SUBCMD": 1,
		"Args": "a1020600696c0900650061ff"
	},
	{
		"LABEL": "0x2e70",
		"Type": "MESSAGE",
		"SUBCMD": 3,
		"SUBCMD2": 675,
		"MSGID": 186,
		"VOICEID": 10184,
		"NameJPN": "鴎",
		"JPN": "「うみちゃんがやってくれたんじゃないのかな」",
		"NameENG": "Kamome",
		"ENG": "\"I think maybe Umi-chan did it?\"",
		"Args": "0b"
	},
	{
		"LABEL": "0x2eb2",
		"Type": "MESSAGE",
		"SUBCMD": 3,
		"SUBCMD2": 677,
		"MSGID": 187,
		"NameJPN": "羽依里",
		"JPN": "「そうなんだ」",
		"NameENG": "Hairi",
		"ENG": "\"Did she?\"",
		"Args": "0b"
	},
	{
		"LABEL": "0x2eda",
		"Type": "MESSAGE",
		"SUBCMD": 3,
		"SUBCMD2": 679,
		"MSGID": 188,
		"JPN": "俺の手を気遣って、やってくれてたんだ。",
		"ENG": "She must have been trying to be considerate of my arm.",
		"Args": "0b"
	},
	{
		"LABEL": "0x2f10",
		"Type": "MESSAGE",
		"SUBCMD": 3,
		"SUBCMD2": 681,
		"MSGID": 189,
		"JPN": "言ってくれればよかったのに。",
		"ENG": "She should have just told me.",
		"Args": "0b"
	},
	{
		"LABEL": "0x2f3c",
		"Type": "IMAGELOAD",
		"SUBCMD": 1,
		"Args": "ab0206008b6c0900650061ff"
	},
	{
		"LABEL": "0x2f4c",
		"Type": "MESSAGE",
		"SUBCMD": 3,
		"SUBCMD2": 685,
		"MSGID": 190,
		"VOICEID": 10185,
		"NameJPN": "鴎",
		"JPN": "「だからてっきりお風呂を手伝うって、洗って欲しいってことかと思って」",
		"NameENG": "Kamome",
		"ENG": "\"So I thought you meant you needed help, like, bathing. Or something...\"",
		"Args": "0b"
	},
	{
		"LABEL": "0x2fa6",
		"Type": "MESSAGE",
		"SUBCMD": 3,
		"SUBCMD2": 687,
		"MSGID": 191,
		"NameJPN": "羽依里",
		"JPN": "「そんなこと頼むか」",
		"NameENG": "Hairi",
		"ENG": "\"Why would I ever want you to do that?\"",
		"Args": "0b"
	},
	{
		"LABEL": "0x2fd4",
		"Type": "MESSAGE",
		"SUBCMD": 3,
		"SUBCMD2": 689,
		"MSGID": 192,
		"NameJPN": "羽依里",
		"JPN": "「そもそも、まだ帰ってなかったのか」",
		"NameENG": "Hairi",
		"ENG": "\"Why are you even still here in the first place?\"",
		"Args": "0b"
	},
	{
		"LABEL": "0x3012",
		"Type": "IMAGELOAD",
		"SUBCMD": 1,
		"Args": "b3020600696c0900650061ff"
	},
	{
		"LABEL": "0x3022",
		"Type": "MESSAGE",
		"SUBCMD": 3,
		"SUBCMD2": 693,
		"MSGID": 193,
		"VOICEID": 10186,
		"NameJPN": "鴎",
		"JPN": "「お風呂手伝うまで帰れないなと思ったから」",
		"NameENG": "Kamome",
		"ENG": "\"Because I thought I couldn't go back until I helped you wash.\"",
		"Args": "0b"
	},
	{
		"LABEL": "0x3062",
		"Type": "IMAGELOAD",
		"SUBCMD": 1,
		"Args": "b70206006d6c0900650061ff"
	},
	{
		"LABEL": "0x3072",
		"Type": "MESSAGE",
		"SUBCMD": 3,
		"SUBCMD2": 697,
		"MSGID": 194,
		"VOICEID": 10187,
		"NameJPN": "鴎",
		"JPN": "「蔵で鏡子さんと話してたよ」",
		"NameENG": "Kamome",
		"ENG": "\"I was chatting with Kyouko-san in the shed.\"",
		"Args": "0b"
	},
	{
		"LABEL": "0x30a4",
		"Type": "MESSAGE",
		"SUBCMD": 3,
		"SUBCMD2": 699,
		"MSGID": 195,
		"NameJPN": "羽依里",
		"JPN": "「それは悪かったな」",
		"NameENG": "Hairi",
		"ENG": "\"That's... my bad, I guess.\"",
		"Args": "0b"
	},
	{
		"LABEL": "0x30d2",
		"Type": "IMAGELOAD",
		"SUBCMD": 1,
		"Args": "bd020600896c0900650061ff"
	},
	{
		"LABEL": "0x30e2",
		"Type": "MESSAGE",
		"SUBCMD": 3,
		"SUBCMD2": 703,
		"MSGID": 196,
		"VOICEID": 10188,
		"NameJPN": "鴎",
		"JPN": "「まぁ、せっかくだから背中ぐらい流そうか？」",
		"NameENG": "Kamome",
		"ENG": "\"Um, I'm already here and all. I can at least scrub your back, if you want.\"",
		"Args": "0b"
	},
	{
		"LABEL": "0x3124",
		"Type": "IMAGELOAD",
		"SUBCMD": 1,
		"Args": "c1020600876c0900650061ff"
	},
	{
		"LABEL": "0x3134",
		"Type": "MESSAGE",
		"SUBCMD": 3,
		"SUBCMD2": 707,
		"MSGID": 197,
		"VOICEID": 10189,
		"NameJPN": "鴎",
		"JPN": "「タオルはつけてね」",
		"NameENG": "Kamome",
		"ENG": "\"After you put a towel on, that is.\"",
		"Args": "0b"
	},
	{
		"LABEL": "0x315e",
		"Type": "MESSAGE",
		"SUBCMD": 3,
		"SUBCMD2": 709,
		"MSGID": 198,
		"NameJPN": "羽依里",
		"JPN": "「……」",
		"NameENG": "Hairi",
		"ENG": "\"......\"",
		"Args": "0b"
	},
	{
		"LABEL": "0x3180",
		"Type": "MESSAGE",
		"SUBCMD": 3,
		"SUBCMD2": 711,
		"MSGID": 199,
		"JPN": "どうなんだ。",
		"ENG": "I've found myself in a quandary.",
		"Args": "0b"
	},
	{
		"LABEL": "0x319c",
		"Type": "MESSAGE",
		"SUBCMD": 3,
		"SUBCMD2": 713,
		"MSGID": 200,
		"JPN": "そこまで意識することじゃないのかな。",
		"ENG": "I guess it's only awkward if you make it awkward.",
		"Args": "0b"
	},
	{
		"LABEL": "0x31d0",
		"Type": "MESSAGE",
		"SUBCMD": 3,
		"SUBCMD2": 715,
		"MSGID": 201,
		"JPN": "小学校の頃に母親に体を洗ってもらったことを、なんとなく思い出した。",
		"ENG": "Memories of my mom bathing me when I was in elementary school came to mind.",
		"Args": "0b"
	},
	{
		"LABEL": "0x3222",
		"Type": "MESSAGE",
		"SUBCMD": 3,
		"SUBCMD2": 717,
		"MSGID": 202,
		"NameJPN": "羽依里",
		"JPN": "「……じゃあ」",
		"NameENG": "Hairi",
		"ENG": "\"...All right.\"",
		"Args": "0b"
	},
	{
		"LABEL": "0x324a",
		"Type": "SE",
		"SUBCMD": 1,
		"Args": "cf0205f50f0300"
	},
	{
		"LABEL": "0x3256",
		"Type": "MESSAGE",
		"SUBCMD": 3,
		"SUBCMD2": 721,
		"MSGID": 203,
		"JPN": "腰にタオルをつけて、湯船からあがる。",
		"ENG": "I wrapped a towel around my waist and stood up.",
		"Args": "0b"
	},
	{
		"LABEL": "0x328a",
		"Type": "IMAGELOAD",
		"SUBCMD": 1,
		"Args": "d30206007b6c0900650061ff"
	},
	{
		"LABEL": "0x329a",
		"Type": "MESSAGE",
		"SUBCMD": 3,
		"SUBCMD2": 725,
		"MSGID": 204,
		"VOICEID": 10190,
		"NameJPN": "鴎",
		"JPN": "「……」",
		"NameENG": "Kamome",
		"ENG": "\"......\"",
		"Args": "0b"
	},
	{
		"LABEL": "0x32b8",
		"Type": "MESSAGE",
		"SUBCMD": 3,
		"SUBCMD2": 727,
		"MSGID": 205,
		"JPN": "あがってきた俺の半裸に、鴎は目をぱちくりさせている。",
		"ENG": "Kamome blinked in surprise upon seeing my half naked body.",
		"Args": "0b"
	},
	{
		"LABEL": "0x32fc",
		"Type": "IMAGELOAD",
		"SUBCMD": 1,
		"Args": "d9020600836c0900650061ff"
	},
	{
		"LABEL": "0x330c",
		"Type": "MESSAGE",
		"SUBCMD": 3,
		"SUBCMD2": 731,
		"MSGID": 206,
		"VOICEID": 10191,
		"NameJPN": "鴎",
		"JPN": "「やっぱりごめん」",
		"NameENG": "Kamome",
		"ENG": "\"Nope, sorry.\"",
		"Args": "0b"
	},
	{
		"LABEL": "0x3334",
		"Type": "IMAGELOAD",
		"SUBCMD": 1,
		"Args": "dd020600816c0900650061ff"
	},
	{
		"LABEL": "0x3344",
		"Type": "MESSAGE",
		"SUBCMD": 3,
		"SUBCMD2": 735,
		"MSGID": 207,
		"VOICEID": 10192,
		"NameJPN": "鴎",
		"JPN": "「無理そう」",
		"NameENG": "Kamome",
		"ENG": "\"This ain't happening.\"",
		"Args": "0b"
	},
	{
		"LABEL": "0x3366",
		"Type": "SE",
		"SUBCMD": 1,
		"Args": "e40205"
	},
	{
		"LABEL": "0x336e",
		"Type": "BGM",
		"SUBCMD": 1,
		"Args": "e502000000007800"
	},
	{
		"LABEL": "0x337a",
		"Type": "CLOSE_WINDOW",
		"SUBCMD": 1,
		"Args": "e702"
	},
	{
		"LABEL": "0x3380",
		"Type": "EQUN",
		"SUBCMD": 0,
		"Args": "3b1a0000"
	},
	{
		"LABEL": "0x3388",
		"Type": "IMAGELOAD",
		"SUBCMD": 0,
		"Args": "0000b800000000000000"
	},
	{
		"LABEL": "0x3396",
		"Type": "INIT",
		"SUBCMD": 0,
		"Args": "01ff"
	},
	{
		"LABEL": "0x339c",
		"Type": "DRAW",
		"SUBCMD": 0,
		"Args": "3c00"
	},
	{
		"LABEL": "0x33a2",
		"Type": "WAIT",
		"SUBCMD": 0,
		"Args": ""
	},
	{
		"LABEL": "0x33a6",
		"Type": "WAIT",
		"SUBCMD": 0,
		"Args": "3c00"
	},
	{
		"LABEL": "0x33ac",
		"Type": "BGM",
		"SUBCMD": 1,
		"Args": "ea02b1860100"
	},
	{
		"LABEL": "0x33b6",
		"Type": "CLOSE_WINDOW",
		"SUBCMD": 1,
		"Args": "f202"
	},
	{
		"LABEL": "0x33bc",
		"Type": "IMAGELOAD",
		"SUBCMD": 0,
		"Args": "00003c00000000000000"
	},
	{
		"LABEL": "0x33ca",
		"Type": "EQUN",
		"SUBCMD": 0,
		"Args": "3b1a0100"
	},
	{
		"LABEL": "0x33d2",
		"Type": "DRAW",
		"SUBCMD": 0,
		"Args": "3c00"
	},
	{
		"LABEL": "0x33d8",
		"Type": "WAIT",
		"SUBCMD": 0,
		"Args": ""
	},
	{
		"LABEL": "0x33dc",
		"Type": "IMAGELOAD",
		"SUBCMD": 1,
		"Args": "f4020100cfb700008002b4007900"
	},
	{
		"LABEL": "0x33ee",
		"Type": "DRAW",
		"SUBCMD": 0,
		"Args": "0f00"
	},
	{
		"LABEL": "0x33f4",
		"Type": "MESSAGE",
		"SUBCMD": 3,
		"SUBCMD2": 758,
		"MSGID": 208,
		"VOICEID": 10193,
		"NameJPN": "鴎",
		"JPN": "「それじゃあ。お邪魔しました」",
		"NameENG": "Kamome",
		"ENG": "\"Anyway, thanks for having me!\"",
		"Args": "0b"
	},
	{
		"LABEL": "0x3428",
		"Type": "MOVE",
		"SUBCMD": 1,
		"Args": "f80201000218009001b400"
	},
	{
		"LABEL": "0x3438",
		"Type": "IMAGELOAD",
		"SUBCMD": 0,
		"Args": "01010aac00007003b4009100"
	},
	{
		"LABEL": "0x3448",
		"Type": "DRAW",
		"SUBCMD": 0,
		"Args": "0f00"
	},
	{
		"LABEL": "0x344e",
		"Type": "MESSAGE",
		"SUBCMD": 3,
		"SUBCMD2": 762,
		"MSGID": 209,
		"VOICEID": 28264,
		"NameJPN": "うみ",
		"JPN": "「かもめさん、ありがとー」",
		"NameENG": "Umi",
		"ENG": "\"Thank you for helping, Kamome-san!\"",
		"Args": "0b"
	},
	{
		"LABEL": "0x3480",
		"Type": "IMAGEUPDATE",
		"SUBCMD": 1,
		"Args": "fc020100bfb7"
	},
	{
		"LABEL": "0x348a",
		"Type": "DRAW",
		"SUBCMD": 0,
		"Args": "0f00"
	},
	{
		"LABEL": "0x3490",
		"Type": "MESSAGE",
		"SUBCMD": 3,
		"SUBCMD2": 766,
		"MSGID": 210,
		"VOICEID": 10195,
		"NameJPN": "鴎",
		"JPN": "「いいえ」",
		"NameENG": "Kamome",
		"ENG": "\"Don't mention it.\"",
		"Args": "0b"
	},
	{
		"LABEL": "0x34b0",
		"Type": "MESSAGE",
		"SUBCMD": 3,
		"SUBCMD2": 768,
		"MSGID": 211,
		"NameJPN": "羽依里",
		"JPN": "「途中まで送るぞ」",
		"NameENG": "Hairi",
		"ENG": "\"I'll walk with you.\"",
		"Args": "0b"
	},
	{
		"LABEL": "0x34dc",
		"Type": "IMAGEUPDATE",
		"SUBCMD": 1,
		"Args": "02030100cfb7"
	},
	{
		"LABEL": "0x34e6",
		"Type": "DRAW",
		"SUBCMD": 0,
		"Args": "0f00"
	},
	{
		"LABEL": "0x34ec",
		"Type": "MESSAGE",
		"SUBCMD": 3,
		"SUBCMD2": 772,
		"MSGID": 212,
		"VOICEID": 10196,
		"NameJPN": "鴎",
		"JPN": "「ありがとう」",
		"NameENG": "Kamome",
		"ENG": "\"Thanks.\"",
		"Args": "0b"
	},
	{
		"LABEL": "0x3510",
		"Type": "RETURN",
		"SUBCMD": 1,
		"Args": "0a03"
	},
	{
		"LABEL": "0x3516",
		"Type": "END",
		"SUBCMD": 3,
		"Args": "0c030080"
	}
]