[
	{
		"LABEL": "0x0",
		"Type": "CLOSE_WINDOW",
		"SUBCMD": 1,
		"Args": "0f00"
	},
	{
		"LABEL": "0x6",
		"Type": "IMAGELOAD",
		"SUBCMD": 0,
		"Args": "00004400000000000000"
	},
	{
		"LABEL": "0x14",
		"Type": "EQUN",
		"SUBCMD": 0,
		"Args": "3b1a0000"
	},
	{
		"LABEL": "0x1c",
		"Type": "DRAW",
		"SUBCMD": 0,
		"Args": "3c00"
	},
	{
		"LABEL": "0x22",
		"Type": "WAIT",
		"SUBCMD": 0,
		"Args": ""
	},
	{
		"LABEL": "0x26",
		"Type": "IMAGELOAD",
		"SUBCMD": 1,
		"Args": "11000100a2ad00008002b4009100"
	},
	{
		"LABEL": "0x38",
		"Type": "MOVE",
		"SUBCMD": 0,
		"Args": "01000000003e02b400"
	},
	{
		"LABEL": "0x46",
		"Type": "MOVE",
		"SUBCMD": 0,
		"Args": "01000218008002b400"
	},
	{
		"LABEL": "0x54",
		"Type": "DRAW",
		"SUBCMD": 0,
		"Args": "0f00"
	},
	{
		"LABEL": "0x5a",
		"Type": "MESSAGE",
		"SUBCMD": 3,
		"SUBCMD2": 20,
		"MSGID": 0,
		"VOICEID": 27742,
		"NameJPN": "うみ",
		"JPN": "「羽依里さん」",
		"NameENG": "Umi",
		"ENG": "\"Hairi-san.\"",
		"Args": "0b"
	},
	{
		"LABEL": "0x80",
		"Type": "MESSAGE",
		"SUBCMD": 3,
		"SUBCMD2": 22,
		"MSGID": 1,
		"JPN": "……",
		"ENG": "......",
		"Args": "0b"
	},
	{
		"LABEL": "0x94",
		"Type": "IMAGEUPDATE",
		"SUBCMD": 1,
		"Args": "1800010076ac"
	},
	{
		"LABEL": "0x9e",
		"Type": "DRAW",
		"SUBCMD": 0,
		"Args": "0f00"
	},
	{
		"LABEL": "0xa4",
		"Type": "MESSAGE",
		"SUBCMD": 3,
		"SUBCMD2": 26,
		"MSGID": 2,
		"VOICEID": 27743,
		"NameJPN": "うみ",
		"JPN": "「羽依里さんお昼ご飯出来たよ」",
		"NameENG": "Umi",
		"ENG": "\"Hairi-san, lunch is ready.\"",
		"Args": "0b"
	},
	{
		"LABEL": "0xda",
		"Type": "MESSAGE",
		"SUBCMD": 3,
		"SUBCMD2": 28,
		"MSGID": 3,
		"NameJPN": "羽依里",
		"JPN": "「あ、うん」",
		"NameENG": "Hairi",
		"ENG": "\"Oh, okay.\"",
		"Args": "0b"
	},
	{
		"LABEL": "0x100",
		"Type": "IMAGEUPDATE",
		"SUBCMD": 1,
		"Args": "1e00010070ac"
	},
	{
		"LABEL": "0x10a",
		"Type": "DRAW",
		"SUBCMD": 0,
		"Args": "0f00"
	},
	{
		"LABEL": "0x110",
		"Type": "MESSAGE",
		"SUBCMD": 3,
		"SUBCMD2": 32,
		"MSGID": 4,
		"VOICEID": 27744,
		"NameJPN": "うみ",
		"JPN": "「何書いてるの？」",
		"NameENG": "Umi",
		"ENG": "\"What're you writing?\"",
		"Args": "0b"
	},
	{
		"LABEL": "0x13a",
		"Type": "MESSAGE",
		"SUBCMD": 3,
		"SUBCMD2": 34,
		"MSGID": 5,
		"JPN": "机に向かって黙々とペンを走らせる俺を珍しそうにうみちゃんがのぞき込む。",
		"ENG": "Umi-chan curiously watched me scribble my pen over the page in silence.",
		"Args": "0b"
	},
	{
		"LABEL": "0x190",
		"Type": "MESSAGE",
		"SUBCMD": 3,
		"SUBCMD2": 36,
		"MSGID": 6,
		"NameJPN": "羽依里",
		"JPN": "「手紙」",
		"NameENG": "Hairi",
		"ENG": "\"Letters.\"",
		"Args": "0b"
	},
	{
		"LABEL": "0x1b2",
		"Type": "IMAGEUPDATE",
		"SUBCMD": 1,
		"Args": "2600010052ac"
	},
	{
		"LABEL": "0x1bc",
		"Type": "DRAW",
		"SUBCMD": 0,
		"Args": "0f00"
	},
	{
		"LABEL": "0x1c2",
		"Type": "MESSAGE",
		"SUBCMD": 3,
		"SUBCMD2": 40,
		"MSGID": 7,
		"VOICEID": 27745,
		"NameJPN": "うみ",
		"JPN": "「手紙……？」",
		"NameENG": "Umi",
		"ENG": "\"Letters?\"",
		"Args": "0b"
	},
	{
		"LABEL": "0x1e8",
		"Type": "IMAGEUPDATE",
		"SUBCMD": 1,
		"Args": "2a00010046ac"
	},
	{
		"LABEL": "0x1f2",
		"Type": "DRAW",
		"SUBCMD": 0,
		"Args": "0f00"
	},
	{
		"LABEL": "0x1f8",
		"Type": "MESSAGE",
		"SUBCMD": 3,
		"SUBCMD2": 44,
		"MSGID": 8,
		"VOICEID": 27746,
		"NameJPN": "うみ",
		"JPN": "「すごいたくさん、書いてるみたいだけど」",
		"NameENG": "Umi",
		"ENG": "\"Woah, that many?\"",
		"Args": "0b"
	},
	{
		"LABEL": "0x238",
		"Type": "MESSAGE",
		"SUBCMD": 3,
		"SUBCMD2": 46,
		"MSGID": 9,
		"JPN": "机に積み上がった手紙の山に目を丸くしている。",
		"ENG": "Her eyes went wide when she saw the massive pile on the desk.",
		"Args": "0b"
	},
	{
		"LABEL": "0x274",
		"Type": "MESSAGE",
		"SUBCMD": 3,
		"SUBCMD2": 48,
		"MSGID": 10,
		"NameJPN": "羽依里",
		"JPN": "「うん」",
		"NameENG": "Hairi",
		"ENG": "\"Yep.\"",
		"Args": "0b"
	},
	{
		"LABEL": "0x296",
		"Type": "MESSAGE",
		"SUBCMD": 3,
		"SUBCMD2": 50,
		"MSGID": 11,
		"NameJPN": "羽依里",
		"JPN": "「たくさん出すんだ」",
		"NameENG": "Hairi",
		"ENG": "\"And I've got a lot more to go.\"",
		"Args": "0b"
	},
	{
		"LABEL": "0x2c4",
		"Type": "IMAGEUPDATE",
		"SUBCMD": 1,
		"Args": "3400010070ac"
	},
	{
		"LABEL": "0x2ce",
		"Type": "DRAW",
		"SUBCMD": 0,
		"Args": "0f00"
	},
	{
		"LABEL": "0x2d4",
		"Type": "MESSAGE",
		"SUBCMD": 3,
		"SUBCMD2": 54,
		"MSGID": 12,
		"VOICEID": 27747,
		"NameJPN": "うみ",
		"JPN": "「一体誰宛なの」",
		"NameENG": "Umi",
		"ENG": "\"Who're they for?\"",
		"Args": "0b"
	},
	{
		"LABEL": "0x2fc",
		"Type": "MESSAGE",
		"SUBCMD": 3,
		"SUBCMD2": 56,
		"MSGID": 13,
		"NameJPN": "羽依里",
		"JPN": "「昔の友達」",
		"NameENG": "Hairi",
		"ENG": "\"Old friends.\"",
		"Args": "0b"
	},
	{
		"LABEL": "0x322",
		"Type": "IMAGEUPDATE",
		"SUBCMD": 1,
		"Args": "3a0001007cac"
	},
	{
		"LABEL": "0x32c",
		"Type": "DRAW",
		"SUBCMD": 0,
		"Args": "0f00"
	},
	{
		"LABEL": "0x332",
		"Type": "MESSAGE",
		"SUBCMD": 3,
		"SUBCMD2": 60,
		"MSGID": 14,
		"VOICEID": 27748,
		"NameJPN": "うみ",
		"JPN": "「多いんだね。昔の友達」",
		"NameENG": "Umi",
		"ENG": "\"That's a lotta friends you have.\"",
		"Args": "0b"
	},
	{
		"LABEL": "0x362",
		"Type": "MESSAGE",
		"SUBCMD": 3,
		"SUBCMD2": 62,
		"MSGID": 15,
		"NameJPN": "羽依里",
		"JPN": "「うん」",
		"NameENG": "Hairi",
		"ENG": "\"Yeah.\"",
		"Args": "0b"
	},
	{
		"LABEL": "0x384",
		"Type": "CLOSE_WINDOW",
		"SUBCMD": 1,
		"Args": "4000"
	},
	{
		"LABEL": "0x38a",
		"Type": "EQUN",
		"SUBCMD": 0,
		"Args": "3b1a0000"
	},
	{
		"LABEL": "0x392",
		"Type": "INIT",
		"SUBCMD": 0,
		"Args": "0100"
	},
	{
		"LABEL": "0x398",
		"Type": "IMAGELOAD",
		"SUBCMD": 0,
		"Args": "0000b800000000000000"
	},
	{
		"LABEL": "0x3a6",
		"Type": "INIT",
		"SUBCMD": 0,
		"Args": "01ff"
	},
	{
		"LABEL": "0x3ac",
		"Type": "DRAW",
		"SUBCMD": 0,
		"Args": "5a00"
	},
	{
		"LABEL": "0x3b2",
		"Type": "WAIT",
		"SUBCMD": 0,
		"Args": ""
	},
	{
		"LABEL": "0x3b6",
		"Type": "WAIT",
		"SUBCMD": 0,
		"Args": "3c00"
	},
	{
		"LABEL": "0x3bc",
		"Type": "MESSAGE",
		"SUBCMD": 3,
		"SUBCMD2": 66,
		"MSGID": 16,
		"JPN": "……",
		"ENG": "......",
		"Args": "0b"
	},
	{
		"LABEL": "0x3d0",
		"Type": "IMAGELOAD",
		"SUBCMD": 1,
		"Args": "480006006eac09006b00dcfe"
	},
	{
		"LABEL": "0x3e0",
		"Type": "MESSAGE",
		"SUBCMD": 3,
		"SUBCMD2": 74,
		"MSGID": 17,
		"VOICEID": 27749,
		"NameJPN": "うみ",
		"JPN": "「羽依里さん」",
		"NameENG": "Umi",
		"ENG": "\"Hairi-san!\"",
		"Args": "0b"
	},
	{
		"LABEL": "0x406",
		"Type": "IMAGELOAD",
		"SUBCMD": 1,
		"Args": "4c00060050ac09006b00dcfe"
	},
	{
		"LABEL": "0x416",
		"Type": "MESSAGE",
		"SUBCMD": 3,
		"SUBCMD2": 78,
		"MSGID": 18,
		"VOICEID": 27750,
		"NameJPN": "うみ",
		"JPN": "「起きてよ」",
		"NameENG": "Umi",
		"ENG": "\"Wake up!\"",
		"Args": "0b"
	},
	{
		"LABEL": "0x43a",
		"Type": "MESSAGE",
		"SUBCMD": 3,
		"SUBCMD2": 80,
		"MSGID": 19,
		"NameJPN": "羽依里",
		"JPN": "「……え」",
		"NameENG": "Hairi",
		"ENG": "\"...Huh...?\"",
		"Args": "0b"
	},
	{
		"LABEL": "0x45e",
		"Type": "CLOSE_WINDOW",
		"SUBCMD": 1,
		"Args": "5200"
	},
	{
		"LABEL": "0x464",
		"Type": "IMAGELOAD",
		"SUBCMD": 0,
		"Args": "00004400000000000000"
	},
	{
		"LABEL": "0x472",
		"Type": "EQUN",
		"SUBCMD": 0,
		"Args": "3b1a0000"
	},
	{
		"LABEL": "0x47a",
		"Type": "IMAGELOAD",
		"SUBCMD": 0,
		"Args": "010052ac00008002b4009100"
	},
	{
		"LABEL": "0x48a",
		"Type": "WIPE",
		"SUBCMD": 0,
		"Args": "0e005d2b5a00"
	},
	{
		"LABEL": "0x494",
		"Type": "WAIT",
		"SUBCMD": 0,
		"Args": "5a00"
	},
	{
		"LABEL": "0x49a",
		"Type": "IMAGEUPDATE",
		"SUBCMD": 1,
		"Args": "5400010028ac"
	},
	{
		"LABEL": "0x4a4",
		"Type": "DRAW",
		"SUBCMD": 0,
		"Args": "0f00"
	},
	{
		"LABEL": "0x4aa",
		"Type": "MESSAGE",
		"SUBCMD": 3,
		"SUBCMD2": 86,
		"MSGID": 20,
		"VOICEID": 27751,
		"NameJPN": "うみ",
		"JPN": "「徹夜で手紙かいてたの？」",
		"NameENG": "Umi",
		"ENG": "\"Were you up all last night doing this?\"",
		"Args": "0b"
	},
	{
		"LABEL": "0x4dc",
		"Type": "MESSAGE",
		"SUBCMD": 3,
		"SUBCMD2": 88,
		"MSGID": 21,
		"NameJPN": "羽依里",
		"JPN": "「う、ん」",
		"NameENG": "Hairi",
		"ENG": "\"Y-Yeah.\"",
		"Args": "0b"
	},
	{
		"LABEL": "0x500",
		"Type": "IMAGEUPDATE",
		"SUBCMD": 1,
		"Args": "5a0001000aac"
	},
	{
		"LABEL": "0x50a",
		"Type": "DRAW",
		"SUBCMD": 0,
		"Args": "0f00"
	},
	{
		"LABEL": "0x510",
		"Type": "MESSAGE",
		"SUBCMD": 3,
		"SUBCMD2": 92,
		"MSGID": 22,
		"VOICEID": 27752,
		"NameJPN": "うみ",
		"JPN": "「ご飯、できてるよ」",
		"NameENG": "Umi",
		"ENG": "\"Lunch is ready.\"",
		"Args": "0b"
	},
	{
		"LABEL": "0x53c",
		"Type": "MESSAGE",
		"SUBCMD": 3,
		"SUBCMD2": 94,
		"MSGID": 23,
		"NameJPN": "羽依里",
		"JPN": "「ありがとう」",
		"NameENG": "Hairi",
		"ENG": "\"Thanks.\"",
		"Args": "0b"
	},
	{
		"LABEL": "0x564",
		"Type": "CLOSE_WINDOW",
		"SUBCMD": 1,
		"Args": "6100"
	},
	{
		"LABEL": "0x56a",
		"Type": "EQUN",
		"SUBCMD": 0,
		"Args": "3b1a0000"
	},
	{
		"LABEL": "0x572",
		"Type": "INIT",
		"SUBCMD": 0,
		"Args": "0100"
	},
	{
		"LABEL": "0x578",
		"Type": "IMAGELOAD",
		"SUBCMD": 0,
		"Args": "0000b800000000000000"
	},
	{
		"LABEL": "0x586",
		"Type": "INIT",
		"SUBCMD": 0,
		"Args": "01ff"
	},
	{
		"LABEL": "0x58c",
		"Type": "DRAW",
		"SUBCMD": 0,
		"Args": "3c00"
	},
	{
		"LABEL": "0x592",
		"Type": "WAIT",
		"SUBCMD": 0,
		"Args": ""
	},
	{
		"LABEL": "0x596",
		"Type": "WAIT",
		"SUBCMD": 0,
		"Args": "3c00"
	},
	{
		"LABEL": "0x59c",
		"Type": "CLOSE_WINDOW",
		"SUBCMD": 1,
		"Args": "6400"
	},
	{
		"LABEL": "0x5a2",
		"Type": "IMAGELOAD",
		"SUBCMD": 0,
		"Args": "00003d00000000000000"
	},
	{
		"LABEL": "0x5b0",
		"Type": "EQUN",
		"SUBCMD": 0,
		"Args": "3b1a0000"
	},
	{
		"LABEL": "0x5b8",
		"Type": "DRAW",
		"SUBCMD": 0,
		"Args": "3c00"
	},
	{
		"LABEL": "0x5be",
		"Type": "WAIT",
		"SUBCMD": 0,
		"Args": ""
	},
	{
		"LABEL": "0x5c2",
		"Type": "MESSAGE",
		"SUBCMD": 3,
		"SUBCMD2": 102,
		"MSGID": 24,
		"JPN": "……",
		"ENG": "......",
		"Args": "0b"
	},
	{
		"LABEL": "0x5d6",
		"Type": "MESSAGE",
		"SUBCMD": 3,
		"SUBCMD2": 105,
		"MSGID": 25,
		"NameJPN": "羽依里",
		"JPN": "「ごちそうさま」",
		"NameENG": "Hairi",
		"ENG": "\"Thanks for the food.\"",
		"Args": "0b"
	},
	{
		"LABEL": "0x600",
		"Type": "MESSAGE",
		"SUBCMD": 3,
		"SUBCMD2": 107,
		"MSGID": 26,
		"NameJPN": "羽依里",
		"JPN": "「片付けとか、お願いしていい？」",
		"NameENG": "Hairi",
		"ENG": "\"Do you mind cleaning up?\"",
		"Args": "0b"
	},
	{
		"LABEL": "0x63a",
		"Type": "IMAGELOAD",
		"SUBCMD": 1,
		"Args": "6d00010052ac00008002b4009100"
	},
	{
		"LABEL": "0x64c",
		"Type": "DRAW",
		"SUBCMD": 0,
		"Args": "0f00"
	},
	{
		"LABEL": "0x652",
		"Type": "MESSAGE",
		"SUBCMD": 3,
		"SUBCMD2": 111,
		"MSGID": 27,
		"VOICEID": 27753,
		"NameJPN": "うみ",
		"JPN": "「いいけど」",
		"NameENG": "Umi",
		"ENG": "\"I guess not.\"",
		"Args": "0b"
	},
	{
		"LABEL": "0x676",
		"Type": "IMAGEUPDATE",
		"SUBCMD": 1,
		"Args": "7100010070ac"
	},
	{
		"LABEL": "0x680",
		"Type": "DRAW",
		"SUBCMD": 0,
		"Args": "0f00"
	},
	{
		"LABEL": "0x686",
		"Type": "MESSAGE",
		"SUBCMD": 3,
		"SUBCMD2": 115,
		"MSGID": 28,
		"VOICEID": 27754,
		"NameJPN": "うみ",
		"JPN": "「まだ、手紙書くの？」",
		"NameENG": "Umi",
		"ENG": "\"You're still writing letters?\"",
		"Args": "0b"
	},
	{
		"LABEL": "0x6b4",
		"Type": "MESSAGE",
		"SUBCMD": 3,
		"SUBCMD2": 117,
		"MSGID": 29,
		"NameJPN": "羽依里",
		"JPN": "「あぁ」",
		"NameENG": "Hairi",
		"ENG": "\"Yeah.\"",
		"Args": "0b"
	},
	{
		"LABEL": "0x6d6",
		"Type": "IMAGEUPDATE",
		"SUBCMD": 1,
		"Args": "7700010028ac"
	},
	{
		"LABEL": "0x6e0",
		"Type": "DRAW",
		"SUBCMD": 0,
		"Args": "0f00"
	},
	{
		"LABEL": "0x6e6",
		"Type": "MESSAGE",
		"SUBCMD": 3,
		"SUBCMD2": 121,
		"MSGID": 30,
		"VOICEID": 27755,
		"NameJPN": "うみ",
		"JPN": "「あれ、何通ぐらいあるんだろ」",
		"NameENG": "Umi",
		"ENG": "\"How many do you have to do?\"",
		"Args": "0b"
	},
	{
		"LABEL": "0x71c",
		"Type": "MESSAGE",
		"SUBCMD": 3,
		"SUBCMD2": 123,
		"MSGID": 31,
		"NameJPN": "羽依里",
		"JPN": "「んー」",
		"NameENG": "Hairi",
		"ENG": "\"Mmm...\"",
		"Args": "0b"
	},
	{
		"LABEL": "0x73e",
		"Type": "MESSAGE",
		"SUBCMD": 3,
		"SUBCMD2": 125,
		"MSGID": 32,
		"NameJPN": "羽依里",
		"JPN": "「３００ぐらいかな」",
		"NameENG": "Hairi",
		"ENG": "\"Around three hundred or so.\"",
		"Args": "0b"
	},
	{
		"LABEL": "0x76c",
		"Type": "IMAGEUPDATE",
		"SUBCMD": 1,
		"Args": "7f0001007cac"
	},
	{
		"LABEL": "0x776",
		"Type": "DRAW",
		"SUBCMD": 0,
		"Args": "0f00"
	},
	{
		"LABEL": "0x77c",
		"Type": "MESSAGE",
		"SUBCMD": 3,
		"SUBCMD2": 129,
		"MSGID": 33,
		"VOICEID": 27756,
		"NameJPN": "うみ",
		"JPN": "「さ!?」",
		"NameENG": "Umi",
		"ENG": "\"Thr―!?\"",
		"Args": "0b"
	},
	{
		"LABEL": "0x79e",
		"Type": "IMAGEUPDATE",
		"SUBCMD": 1,
		"Args": "83000100c2ae"
	},
	{
		"LABEL": "0x7a8",
		"Type": "DRAW",
		"SUBCMD": 0,
		"Args": "0f00"
	},
	{
		"LABEL": "0x7ae",
		"Type": "MESSAGE",
		"SUBCMD": 3,
		"SUBCMD2": 133,
		"MSGID": 34,
		"VOICEID": 27757,
		"NameJPN": "うみ",
		"JPN": "「友達多いってレベルじゃない……」",
		"NameENG": "Umi",
		"ENG": "\"That's... a little more than a lot.\"",
		"Args": "0b"
	},
	{
		"LABEL": "0x7e8",
		"Type": "CLOSE_WINDOW",
		"SUBCMD": 1,
		"Args": "8800"
	},
	{
		"LABEL": "0x7ee",
		"Type": "EQUN",
		"SUBCMD": 0,
		"Args": "3b1a0000"
	},
	{
		"LABEL": "0x7f6",
		"Type": "INIT",
		"SUBCMD": 0,
		"Args": "0100"
	},
	{
		"LABEL": "0x7fc",
		"Type": "IMAGELOAD",
		"SUBCMD": 0,
		"Args": "0000b800000000000000"
	},
	{
		"LABEL": "0x80a",
		"Type": "INIT",
		"SUBCMD": 0,
		"Args": "01ff"
	},
	{
		"LABEL": "0x810",
		"Type": "DRAW",
		"SUBCMD": 0,
		"Args": "3c00"
	},
	{
		"LABEL": "0x816",
		"Type": "WAIT",
		"SUBCMD": 0,
		"Args": ""
	},
	{
		"LABEL": "0x81a",
		"Type": "WAIT",
		"SUBCMD": 0,
		"Args": "3c00"
	},
	{
		"LABEL": "0x820",
		"Type": "EQUN",
		"SUBCMD": 1,
		"Args": "8b00d11b0200"
	},
	{
		"LABEL": "0x82a",
		"Type": "CLOSE_WINDOW",
		"SUBCMD": 1,
		"Args": "8e00"
	},
	{
		"LABEL": "0x830",
		"Type": "IMAGELOAD",
		"SUBCMD": 0,
		"Args": "00004800000000000000"
	},
	{
		"LABEL": "0x83e",
		"Type": "EQUN",
		"SUBCMD": 0,
		"Args": "3b1a0000"
	},
	{
		"LABEL": "0x846",
		"Type": "DRAW",
		"SUBCMD": 0,
		"Args": "3c00"
	},
	{
		"LABEL": "0x84c",
		"Type": "WAIT",
		"SUBCMD": 0,
		"Args": ""
	},
	{
		"LABEL": "0x850",
		"Type": "MESSAGE",
		"SUBCMD": 3,
		"SUBCMD2": 144,
		"MSGID": 35,
		"JPN": "手紙をひたすら書いていると……",
		"ENG": "As I scribbled out letter after letter...",
		"Args": "0b"
	},
	{
		"LABEL": "0x87e",
		"Type": "MESSAGE",
		"SUBCMD": 3,
		"SUBCMD2": 146,
		"MSGID": 36,
		"JPN": "不思議と、鴎の気持ちが分かるような気がした。",
		"ENG": "I started to feel a strange sort of kinship with Kamome.",
		"Args": "0b"
	},
	{
		"LABEL": "0x8ba",
		"Type": "MESSAGE",
		"SUBCMD": 3,
		"SUBCMD2": 150,
		"MSGID": 37,
		"JPN": "幼い頃、鴎が、会ったことも無い本の読者に手紙を書いている。",
		"ENG": "Back in her childhood, she'd sent pages of letters to strangers, just like I was doing.",
		"Args": "0b"
	},
	{
		"LABEL": "0x904",
		"Type": "MESSAGE",
		"SUBCMD": 3,
		"SUBCMD2": 152,
		"MSGID": 38,
		"JPN": "返事が来るかは分からない。",
		"ENG": "There was no guarantee anyone would reply.",
		"Args": "0b"
	},
	{
		"LABEL": "0x92e",
		"Type": "MESSAGE",
		"SUBCMD": 3,
		"SUBCMD2": 154,
		"MSGID": 39,
		"JPN": "読んでくれるかさえ。",
		"ENG": "Or that they'd even read them.",
		"Args": "0b"
	},
	{
		"LABEL": "0x952",
		"Type": "MESSAGE",
		"SUBCMD": 3,
		"SUBCMD2": 157,
		"MSGID": 40,
		"JPN": "それでも、彼女はきっと、楽しかったんだろう。",
		"ENG": "But there was no doubt in my mind that Kamome had enjoyed every second of it.",
		"Args": "0b"
	},
	{
		"LABEL": "0x98e",
		"Type": "MESSAGE",
		"SUBCMD": 3,
		"SUBCMD2": 159,
		"MSGID": 41,
		"JPN": "俺も今、疲れ果てた気持ちで、だけど、わくわくしながら手紙を書いていた。",
		"ENG": "And as exhausted as I was, the same could be said for me.",
		"Args": "0b"
	},
	{
		"LABEL": "0x9e4",
		"Type": "MESSAGE",
		"SUBCMD": 3,
		"SUBCMD2": 161,
		"MSGID": 42,
		"JPN": "…………",
		"ENG": ".........",
		"Args": "0b"
	},
	{
		"LABEL": "0x9fc",
		"Type": "CLOSE_WINDOW",
		"SUBCMD": 1,
		"Args": "a400"
	},
	{
		"LABEL": "0xa02",
		"Type": "IMAGELOAD",
		"SUBCMD": 0,
		"Args": "0208bb00100000000000"
	},
	{
		"LABEL": "0xa10",
		"Type": "EQUN",
		"SUBCMD": 0,
		"Args": "3b1a0000"
	},
	{
		"LABEL": "0xa18",
		"Type": "INIT",
		"SUBCMD": 0,
		"Args": "01ff"
	},
	{
		"LABEL": "0xa1e",
		"Type": "DRAW",
		"SUBCMD": 0,
		"Args": "5a00"
	},
	{
		"LABEL": "0xa24",
		"Type": "WAIT",
		"SUBCMD": 0,
		"Args": "5a00"
	},
	{
		"LABEL": "0xa2a",
		"Type": "IMAGELOAD",
		"SUBCMD": 0,
		"Args": "0000bb00000000000000"
	},
	{
		"LABEL": "0xa38",
		"Type": "INIT",
		"SUBCMD": 0,
		"Args": "0208"
	},
	{
		"LABEL": "0xa3e",
		"Type": "DRAW",
		"SUBCMD": 0,
		"Args": ""
	},
	{
		"LABEL": "0xa42",
		"Type": "MESSAGE",
		"SUBCMD": 3,
		"SUBCMD2": 166,
		"MSGID": 43,
		"JPN": "……",
		"ENG": "......",
		"Args": "0b"
	},
	{
		"LABEL": "0xa56",
		"Type": "MESSAGE",
		"SUBCMD": 3,
		"SUBCMD2": 168,
		"MSGID": 44,
		"VOICEID": 27758,
		"NameJPN": "声",
		"JPN": "「……さん」",
		"NameENG": "Voice",
		"ENG": "\"...san.\"",
		"Args": "0b"
	},
	{
		"LABEL": "0xa78",
		"Type": "MESSAGE",
		"SUBCMD": 3,
		"SUBCMD2": 170,
		"MSGID": 45,
		"VOICEID": 27759,
		"NameJPN": "声",
		"JPN": "「羽依里さーん」",
		"NameENG": "Voice",
		"ENG": "\"Hairi-saaan!\"",
		"Args": "0b"
	},
	{
		"LABEL": "0xa9e",
		"Type": "EQUN",
		"SUBCMD": 1,
		"Args": "ac00d11b0000"
	},
	{
		"LABEL": "0xaa8",
		"Type": "CLOSE_WINDOW",
		"SUBCMD": 1,
		"Args": "ad00"
	},
	{
		"LABEL": "0xaae",
		"Type": "IMAGELOAD",
		"SUBCMD": 0,
		"Args": "00004400000000000000"
	},
	{
		"LABEL": "0xabc",
		"Type": "EQUN",
		"SUBCMD": 0,
		"Args": "3b1a0000"
	},
	{
		"LABEL": "0xac4",
		"Type": "WIPE",
		"SUBCMD": 0,
		"Args": "0e005d2b5a00"
	},
	{
		"LABEL": "0xace",
		"Type": "WAIT",
		"SUBCMD": 0,
		"Args": ""
	},
	{
		"LABEL": "0xad2",
		"Type": "MESSAGE",
		"SUBCMD": 3,
		"SUBCMD2": 175,
		"MSGID": 46,
		"NameJPN": "羽依里",
		"JPN": "「ん……あれ」",
		"NameENG": "Hairi",
		"ENG": "\"Mh... Wha...?\"",
		"Args": "0b"
	},
	{
		"LABEL": "0xafa",
		"Type": "MESSAGE",
		"SUBCMD": 3,
		"SUBCMD2": 177,
		"MSGID": 47,
		"JPN": "机から頭をあげる。",
		"ENG": "I raised my head off the table.",
		"Args": "0b"
	},
	{
		"LABEL": "0xb1c",
		"Type": "IMAGELOAD",
		"SUBCMD": 1,
		"Args": "b3000100a0ac00008002b4009100"
	},
	{
		"LABEL": "0xb2e",
		"Type": "DRAW",
		"SUBCMD": 0,
		"Args": "0f00"
	},
	{
		"LABEL": "0xb34",
		"Type": "MESSAGE",
		"SUBCMD": 3,
		"SUBCMD2": 181,
		"MSGID": 48,
		"JPN": "うみちゃんが、呆れた顔で立っていた。",
		"ENG": "Umi-chan peered at me with an exasperated look on her face.",
		"Args": "0b"
	},
	{
		"LABEL": "0xb68",
		"Type": "IMAGEUPDATE",
		"SUBCMD": 1,
		"Args": "b7000100a6ac"
	},
	{
		"LABEL": "0xb72",
		"Type": "DRAW",
		"SUBCMD": 0,
		"Args": "0f00"
	},
	{
		"LABEL": "0xb78",
		"Type": "MESSAGE",
		"SUBCMD": 3,
		"SUBCMD2": 185,
		"MSGID": 49,
		"VOICEID": 27760,
		"NameJPN": "うみ",
		"JPN": "「もう、机で寝てぇ……」",
		"NameENG": "Umi",
		"ENG": "\"Sleeping at your desk? Come on.\"",
		"Args": "0b"
	},
	{
		"LABEL": "0xba8",
		"Type": "MESSAGE",
		"SUBCMD": 3,
		"SUBCMD2": 187,
		"MSGID": 50,
		"NameJPN": "羽依里",
		"JPN": "「ん……」",
		"NameENG": "Hairi",
		"ENG": "\"Ngh...\"",
		"Args": "0b"
	},
	{
		"LABEL": "0xbcc",
		"Type": "MESSAGE",
		"SUBCMD": 3,
		"SUBCMD2": 189,
		"MSGID": 51,
		"NameJPN": "羽依里",
		"JPN": "「体が痛い」",
		"NameENG": "Hairi",
		"ENG": "\"I'm all achy...\"",
		"Args": "0b"
	},
	{
		"LABEL": "0xbf2",
		"Type": "IMAGEUPDATE",
		"SUBCMD": 1,
		"Args": "bf0001008eac"
	},
	{
		"LABEL": "0xbfc",
		"Type": "DRAW",
		"SUBCMD": 0,
		"Args": "0f00"
	},
	{
		"LABEL": "0xc02",
		"Type": "MESSAGE",
		"SUBCMD": 3,
		"SUBCMD2": 193,
		"MSGID": 52,
		"VOICEID": 27761,
		"NameJPN": "うみ",
		"JPN": "「休むならちゃんと横にならないと」",
		"NameENG": "Umi",
		"ENG": "\"If you're sleepy, you should just lie down.\"",
		"Args": "0b"
	},
	{
		"LABEL": "0xc3c",
		"Type": "MESSAGE",
		"SUBCMD": 3,
		"SUBCMD2": 195,
		"MSGID": 53,
		"NameJPN": "羽依里",
		"JPN": "「うんでも、大丈夫」",
		"NameENG": "Hairi",
		"ENG": "\"You're right, but I'll be okay.\"",
		"Args": "0b"
	},
	{
		"LABEL": "0xc6a",
		"Type": "MESSAGE",
		"SUBCMD": 3,
		"SUBCMD2": 197,
		"MSGID": 54,
		"NameJPN": "羽依里",
		"JPN": "「書き終わったから」",
		"NameENG": "Hairi",
		"ENG": "\"I'm all finished.\"",
		"Args": "0b"
	},
	{
		"LABEL": "0xc98",
		"Type": "IMAGEUPDATE",
		"SUBCMD": 1,
		"Args": "c700010046ac"
	},
	{
		"LABEL": "0xca2",
		"Type": "DRAW",
		"SUBCMD": 0,
		"Args": "0f00"
	},
	{
		"LABEL": "0xca8",
		"Type": "MESSAGE",
		"SUBCMD": 3,
		"SUBCMD2": 201,
		"MSGID": 55,
		"VOICEID": 27762,
		"NameJPN": "うみ",
		"JPN": "「え」",
		"NameENG": "Umi",
		"ENG": "\"What?\"",
		"Args": "0b"
	},
	{
		"LABEL": "0xcc6",
		"Type": "IMAGEUPDATE",
		"SUBCMD": 1,
		"Args": "cb00010028ac"
	},
	{
		"LABEL": "0xcd0",
		"Type": "DRAW",
		"SUBCMD": 0,
		"Args": "0f00"
	},
	{
		"LABEL": "0xcd6",
		"Type": "MESSAGE",
		"SUBCMD": 3,
		"SUBCMD2": 205,
		"MSGID": 56,
		"VOICEID": 27763,
		"NameJPN": "うみ",
		"JPN": "「昨日も書いてたの？」",
		"NameENG": "Umi",
		"ENG": "\"Were you writing for two whole days?\"",
		"Args": "0b"
	},
	{
		"LABEL": "0xd04",
		"Type": "IMAGEUPDATE",
		"SUBCMD": 1,
		"Args": "cf00010068ae"
	},
	{
		"LABEL": "0xd0e",
		"Type": "DRAW",
		"SUBCMD": 0,
		"Args": "0f00"
	},
	{
		"LABEL": "0xd14",
		"Type": "MESSAGE",
		"SUBCMD": 3,
		"SUBCMD2": 209,
		"MSGID": 57,
		"VOICEID": 27764,
		"NameJPN": "うみ",
		"JPN": "「わ。これ、すごい量……」",
		"NameENG": "Umi",
		"ENG": "\"Wow, this is crazy.\"",
		"Args": "0b"
	},
	{
		"LABEL": "0xd46",
		"Type": "MESSAGE",
		"SUBCMD": 3,
		"SUBCMD2": 211,
		"MSGID": 58,
		"NameJPN": "羽依里",
		"JPN": "「出さないと」",
		"NameENG": "Hairi",
		"ENG": "\"Gotta send them off now.\"",
		"Args": "0b"
	},
	{
		"LABEL": "0xd6e",
		"Type": "IMAGEUPDATE",
		"SUBCMD": 1,
		"Args": "d500010014ae"
	},
	{
		"LABEL": "0xd78",
		"Type": "DRAW",
		"SUBCMD": 0,
		"Args": "0f00"
	},
	{
		"LABEL": "0xd7e",
		"Type": "MESSAGE",
		"SUBCMD": 3,
		"SUBCMD2": 215,
		"MSGID": 59,
		"VOICEID": 27765,
		"NameJPN": "うみ",
		"JPN": "「え？」",
		"NameENG": "Umi",
		"ENG": "\"Wha...?\"",
		"Args": "0b"
	},
	{
		"LABEL": "0xd9e",
		"Type": "MESSAGE",
		"SUBCMD": 3,
		"SUBCMD2": 217,
		"MSGID": 60,
		"NameJPN": "羽依里",
		"JPN": "「手紙」",
		"NameENG": "Hairi",
		"ENG": "\"The letters.\"",
		"Args": "0b"
	},
	{
		"LABEL": "0xdc0",
		"Type": "MESSAGE",
		"SUBCMD": 3,
		"SUBCMD2": 219,
		"MSGID": 61,
		"NameJPN": "羽依里",
		"JPN": "「郵便局に持って行く」",
		"NameENG": "Hairi",
		"ENG": "\"Gonna drop them by the post office real quick.\"",
		"Args": "0b"
	},
	{
		"LABEL": "0xdf0",
		"Type": "IMAGEUPDATE",
		"SUBCMD": 1,
		"Args": "dd0001007cac"
	},
	{
		"LABEL": "0xdfa",
		"Type": "DRAW",
		"SUBCMD": 0,
		"Args": "0f00"
	},
	{
		"LABEL": "0xe00",
		"Type": "MESSAGE",
		"SUBCMD": 3,
		"SUBCMD2": 223,
		"MSGID": 62,
		"VOICEID": 27766,
		"NameJPN": "うみ",
		"JPN": "「全部!?」",
		"NameENG": "Umi",
		"ENG": "\"All of them!?\"",
		"Args": "0b"
	},
	{
		"LABEL": "0xe24",
		"Type": "MESSAGE",
		"SUBCMD": 3,
		"SUBCMD2": 225,
		"MSGID": 63,
		"NameJPN": "羽依里",
		"JPN": "「もちろん」",
		"NameENG": "Hairi",
		"ENG": "\"Of course.\"",
		"Args": "0b"
	},
	{
		"LABEL": "0xe4a",
		"Type": "RETURN",
		"SUBCMD": 1,
		"Args": "e700"
	},
	{
		"LABEL": "0xe50",
		"Type": "END",
		"SUBCMD": 3,
		"Args": "e9000080"
	}
]